Workbook
Name _Hlk231065246: 'DATOS GENERALES'!$H$165

Sheet DATOS GENERALES
A1: FECHA | B1: NOMBRE COMPLETO | C1: ID/CC/DNI | D1: PASAPORTE | E1: PAIS | F1: ESTADO | G1: CIUDAD | H1: DIRECCION | I1: COD POSTAL | J1: CORREO | K1: TELEFONO | L1: TELEGRAM | M1: PRODUCTO / MATERIAL | N1: MONTO | O1: REF | P1: BANK | Q1: LIDER | R1: CIS/ MANDATE | S1: PASAPORTE + 3 MESES | T1: PASAPORTES QUE VENCEN EN 2026
A2: 45918.771 | B2: ALEJANDRA GALLEGO RAMÍREZ | C2: 1088244700 | D2: N/A | E2: COLOMBIA | F2: RISARALDA | G2: PEREIRA | H2: CALLE 67 N 26 55 CUBA | I2: 660005 | J2: alejandragallegoramirez@yahoo.es | K2: (+57) 3146792869 | L2: @ALEJA1324 | M2: 1Q+1N+2V | N2: 200000 | O2: M5603677 | P2: NEQUI | Q2: JOHANA CASTAÑEDA | R2: ENVIADO | S2: N/A
A3: 46114 | B3: ALEJANDRA MARIA BETANCUR OSORIO | C3: 25235412 | D3: BD328207 | E3: COLOMBIA | F3: ANTIOQUIA | G3: MEDELLIN | H3: CR 78A CL 52 SUR - 76 INTERIOR 3 | I3: 050018 | J3: aleja.betos101178@gmail.com | K3: (+57) 3146253152 | L3: @AlejaBetos | M3: 2Q+1V | N3: 100000 | O3: M18737535 | P3: NEQUI | Q3: JOHANA CASTAÑEDA | R3: ENVIADO | S3: VIGENTE
A4: 45817.615 | B4: ALEXANDER MARIN CASTAÑEDA | C4: 10018741 | D4: AT116472 | E4: COLOMBIA | F4: RISARALDA | G4: PEREIRA | H4: CLL 86 # 38 A 08 MZ 11 CS 2 | I4: 660001 | J4: almariny@gmail.com | K4: (+57) 3007352646 | L4: @alexmarin73 | M4: 10Q | N4: 200000 | O4: M15574612 | P4: NEQUI | Q4: JOHANA CASTAÑEDA | R4: ENVIADO | S4: VENCIDO | T4: 46280
A5: 45818.615 | B5: ALEXANDER MARIN CASTAÑEDA | C5: 10018741 | D5: AT116472 | E5: COLOMBIA | F5: RISARALDA | G5: PEREIRA | H5: CLL 86 # 38 A 08 MZ 11 CS 2 | I5: 660001 | J5: almariny@gmail.com | K5: (+57) 3007352646 | L5: @alexmarin73 | M5: 10Q | N5: 200000 | O5: M10446824 | P5: NEQUI | Q5: JOHANA CASTAÑEDA | R5: ENVIADO | S5: VENCIDO | T5: 46280
A6: 45824.615 | B6: ALEXANDER MARIN CASTAÑEDA | C6: 10018741 | D6: AT116472 | E6: COLOMBIA | F6: RISARALDA | G6: PEREIRA | H6: CLL 86 # 38 A 08 MZ 11 CS 2 | I6: 660001 | J6: almariny@gmail.com | K6: (+57) 3007352646 | L6: @alexmarin73 | M6: 10Q | N6: 200000 | O6: M9579646 | P6: NEQUI | Q6: JOHANA CASTAÑEDA | R6: ENVIADO | S6: VENCIDO | T6: 46280
A7: 45831.615 | B7: ALEXANDER MARIN CASTAÑEDA | C7: 10018741 | D7: AT116472 | E7: COLOMBIA | F7: RISARALDA | G7: PEREIRA | H7: CLL 86 # 38 A 08 MZ 11 CS 2 | I7: 660001 | J7: almariny@gmail.com | K7: (+57) 3007352646 | L7: @alexmarin73 | M7: 10Q | N7: 200000 | O7: M8828857 | P7: NEQUI | Q7: JOHANA CASTAÑEDA | R7: ENVIADO | S7: VENCIDO | T7: 46280
A8: 45836.615 | B8: ALEXANDER MARIN CASTAÑEDA | C8: 10018741 | D8: AT116472 | E8: COLOMBIA | F8: RISARALDA | G8: PEREIRA | H8: CLL 86 # 38 A 08 MZ 11 CS 2 | I8: 660001 | J8: almariny@gmail.com | K8: (+57) 3007352646 | L8: @alexmarin73 | M8: 5Q | N8: 500000 | O8: M11116688 | P8: NEQUI | Q8: JOHANA CASTAÑEDA | R8: ENVIADO | S8: VENCIDO | T8: 46280
A9: 45850 | B9: ALEXANDER MARIN CASTAÑEDA | C9: 10018741 | D9: AT116472 | E9: COLOMBIA | F9: RISARALDA | G9: PEREIRA | H9: CLL 86 # 38 A 08 MZ 11 CS 2 | I9: 660001 | J9: almariny@gmail.com | K9: (+57) 3007352646 | L9: @alexmarin73 | M9: 2Q+5N+2V | N9: 300000 | O9: M15993509 | P9: NEQUI | Q9: JOHANA CASTAÑEDA | R9: ENVIADO | S9: VENCIDO | T9: 46280
A10: 45889 | B10: ALEXANDER MARIN CASTAÑEDA | C10: 10018741 | D10: AT116472 | E10: COLOMBIA | F10: RISARALDA | G10: PEREIRA | H10: CLL 86 # 38 A 08 MZ 11 CS 2 | I10: 660001 | J10: almariny@gmail.com | K10: (+57) 3007352646 | L10: @alexmarin73 | M10: 4Q+5N+2V | N10: 200000 | O10: M13915153 | P10: NEQUI | Q10: JOHANA CASTAÑEDA | R10: ENVIADO | S10: VENCIDO | T10: 46280
A11: 45972 | B11: ALEXANDER MARIN CASTAÑEDA | C11: 10018741 | D11: AT116472 | E11: COLOMBIA | F11: RISARALDA | G11: PEREIRA | H11: CLL 86 # 38 A 08 MZ 11 CS 2 | I11: 660001 | J11: almariny@gmail.com | K11: (+57) 3007352646 | L11: @alexmarin73 | M11: COMODIN | N11: 100000 | O11: M06652822 | P11: NEQUI | Q11: JOHANA CASTAÑEDA | R11: ENVIADO | S11: VENCIDO | T11: 46280
A12: 45998 | B12: ALEXANDER MARIN CASTAÑEDA | C12: 10018741 | D12: AT116472 | E12: COLOMBIA | F12: RISARALDA | G12: PEREIRA | H12: CLL 86 # 38 A 08 MZ 11 CS 2 | I12: 660001 | J12: almariny@gmail.com | K12: (+57) 3007352646 | L12: @alexmarin73 | M12: COMODÍN | N12: 100000 | O12: M10128570 | P12: NEQUI | Q12: JOHANA CASTAÑEDA | R12: ENVIADO | S12: VENCIDO | T12: 46280
A13: 46014 | B13: ALEXANDER MARIN CASTAÑEDA | C13: 10018741 | D13: AT116472 | E13: COLOMBIA | F13: RISARALDA | G13: PEREIRA | H13: CLL 86 # 38 A 08 MZ 11 CS 2 | I13: 660001 | J13: almariny@gmail.com | K13: (+57) 3007352646 | L13: @alexmarin73 | M13: // | N13: 100000 | O13: M20655483 | P13: NEQUI | Q13: JOHANA CASTAÑEDA | R13: ENVIADO | S13: VENCIDO | T13: 46280
A14: 46049 | B14: ALEXANDER MARIN CASTAÑEDA | C14: 10018741 | D14: AT116472 | E14: COLOMBIA | F14: RISARALDA | G14: PEREIRA | H14: CLL 86 # 38 A 08 MZ 11 CS 2 | I14: 660001 | J14: almariny@gmail.com | K14: (+57) 3007352646 | L14: @alexmarin73 | M14: 1ZIMCOIN | N14: 500000 | O14: M05036639 | P14: NEQUI | Q14: JOHANA CASTAÑEDA | R14: ENVIADO | S14: VENCIDO | T14: 46280
A15: 46053 | B15: ALEXANDER MARIN CASTAÑEDA | C15: 10018741 | D15: AT116472 | E15: COLOMBIA | F15: RISARALDA | G15: PEREIRA | H15: CLL 86 # 38 A 08 MZ 11 CS 2 | I15: 660001 | J15: almariny@gmail.com | K15: (+57) 3007352646 | L15: @alexmarin73 | M15: 12Q | N15: 300000 | O15: M06363620 | P15: NEQUI | Q15: JOHANA CASTAÑEDA | R15: ENVIADO | S15: VENCIDO | T15: 46280
A16: 46014 | B16: ALIDA FRANCY OVIEDO LOZADA | C16: 55179153 | D16: BH590607 | E16: COLOMBIA | F16: HUILA | G16: NEIVA | H16: CL 7 # 1D – 104 | I16: 410001 | J16: frjuteamo@gmail.com | K16: (+57) 3112441923 | L16: @Francy8576 | M16: 10Q+5N+2V | N16: 400000 | O16: M16502846 | P16: NEQUI | Q16: JOHANA CASTAÑEDA | R16: ENVIADO | S16: VIGENTE
A17: 46128 | B17: ANA BEATRIZ CARIAS PINO | C17: 7148008 | D17: N/A | E17: COLOMBIA | F17: RISARALDA | G17: PEREIRA | H17: CL 73 KR 37 – 26 CASA 46 PISO 1 | I17: 660006 | J17: beaaj17@gmail.com | K17: (+57) 3136229468 | L17: @Karia1728 | M17: 1Q | N17: 0 | O17: GIRO RULETA | P17: N/A | Q17: JOHANA CASTAÑEDA | R17: ENVIADO | S17: N/A
A18: 46128 | B18: ANA BEATRIZ CARIAS PINO | C18: 7148008 | D18: N/A | E18: COLOMBIA | F18: RISARALDA | G18: PEREIRA | H18: CL 73 KR 37 – 26 CASA 46 PISO 1 | I18: 660006 | J18: beaaj17@gmail.com | K18: (+57) 3136229468 | L18: @Karia1728 | M18: 2Q | N18: 100000 | O18: M07700283 | P18: NEQUI | Q18: JOHANA CASTAÑEDA | R18: ENVIADO | S18: N/A
A19: 45832.522 | B19: ANA ISABEL VALENCIA MESA | C19: 41927246 | D19: AX328658 | E19: COLOMBIA | F19: QUINDIO | G19: SALENTO | H19: BARRIO ALDEA ARTESANO BLQ A C 201 | I19: 631028 | J19: anavalenciamesa50@gmail.com | K19: (+57) 3113718240 | L19: @Anais50 | M19: 5Q | N19: 120000 | O19: M2441966 | P19: NEQUI | Q19: JOHANA CASTAÑEDA | R19: ENVIADO | S19: VIGENTE
A20: 45856 | B20: ANAYIBER CARVAJAL CESPEDES | C20: 24587181 | D20: AT403520 | E20: COLOMBIA | F20: RISARALDA | G20: PEREIRA | H20: MNZ 16 CS 11 POBLADO II | I20: 660004 | J20: acarvajal077@gmail.com | K20: (+57) 3147530129 | L20: @CELESTIALJC | M20: 2Q+2N | N20: 200000 | O20: 0000099756 | P20: BANCOLOMBIA | Q20: JOHANA CASTAÑEDA | R20: ENVIADO | S20: VIGENTE | T20: 46365
A21: 45891 | B21: ANDRES MAURICIO MURILLO BALLESTEROS | C21: 75079176 | D21: N/A | E21: COLOMBIA | F21: CALDAS | G21: SALAMINA | H21: CALLE 3 NÚMERO 8-42 | I21: 172001 | J21: maomu2@yahoo.es | K21: (+57) 3218075324 | L21: SIN REGISTRO | M21: 2Q+3N | N21: 300000 | O21: 20431 | P21: DAVIVIENDA | Q21: JOHANA CASTAÑEDA | R21: ENVIADO | S21: N/A
A22: 46003 | B22: ANGEL ALCIDES PAZMIÑO VASCONEZ | C22: 1802036838 | D22: B0083917 | E22: ECUADOR | F22: GUAYAS | G22: MILAGRO | H22: ARIJANGO JIMENEZ 5-45-5 O ENRIQUE ESPIII | I22: 091701 | J22: angelpazminos1965@gmail.com | K22: (+593) 969528889 | L22: @pazmino17 | M22: 2Q | N22: 100000 | O22: M23064602 | P22: NEQUI | Q22: JOHANA CASTAÑEDA | R22: ENVIADO | S22: VIGENTE
A23: 45714.695 | B23: ANGEL RAMIRO TRUJILLO TRUJILLO | C23: 98146902 | D23: N/A | E23: COLOMBIA | F23: NARIÑO | G23: LINARES | H23: LINARES | I23: 526040 | J23: angel3136538260@gmail.com | K23: (+57) 3177801277 | L23: SIN REGISTRO | M23: 1Q | N23: 100000 | O23: 056625 | P23: REDEBAN | Q23: JOHANA CASTAÑEDA | R23: ENVIADO | S23: N/A
A24: 45763.695 | B24: ANGEL RAMIRO TRUJILLO TRUJILLO | C24: 98146902 | D24: N/A | E24: COLOMBIA | F24: NARIÑO | G24: LINARES | H24: LINARES | I24: 526040 | J24: angel3136538260@gmail.com | K24: (+57) 3177801277 | L24: SIN REGISTRO | M24: 1Q | N24: 120000 | O24: 094218 | P24: REDEBAN | Q24: JOHANA CASTAÑEDA | R24: ENVIADO | S24: N/A
A25: 45822.695 | B25: ANGEL RAMIRO TRUJILLO TRUJILLO | C25: 98146902 | D25: N/A | E25: COLOMBIA | F25: NARIÑO | G25: LINARES | H25: LINARES | I25: 526040 | J25: angel3136538260@gmail.com | K25: (+57) 3177801277 | L25: SIN REGISTRO | M25: 1Q | N25: 120000 | O25: 043430 | P25: REDEBAN | Q25: JOHANA CASTAÑEDA | R25: ENVIADO | S25: N/A
A26: 45853.695 | B26: ANGEL RAMIRO TRUJILLO TRUJILLO | C26: 98146902 | D26: N/A | E26: COLOMBIA | F26: NARIÑO | G26: LINARES | H26: LINARES | I26: 526040 | J26: angel3136538260@gmail.com | K26: (+57) 3177801277 | L26: SIN REGISTRO | M26: 2Q+2N | N26: 220000 | O26: M23228079 | P26: NEQUI | Q26: JOHANA CASTAÑEDA | R26: ENVIADO | S26: N/A
A27: 46056 | B27: ANGEL RAMIRO TRUJILLO TRUJILLO | C27: 98146902 | D27: N/A | E27: COLOMBIA | F27: NARIÑO | G27: LINARES | H27: LINARES | I27: 526040 | J27: angel3136538260@gmail.com | K27: (+57) 3177801277 | L27: SIN REGISTRO | M27: 6Q | N27: 150000 | O27: M08491040 | P27: NEQUI | Q27: JOHANA CASTAÑEDA | R27: ENVIADO | S27: N/A
A28: 45811.811 | B28: ANGELA HILDA CANO RUDAS | C28: 30301760 | D28: BF287115 | E28: COLOMBIA | F28: CALDAS | G28: MANIZALES | H28: CLL 19 KR 39-10 | I28: 170004 | J28: canoangela302@gmail.com | K28: (+57) 3234756614 | L28: @angelacano | M28: 10Q | N28: 200000 | O28: M6713334 | P28: NEQUI | Q28: JOHANA CASTAÑEDA | R28: ENVIADO | S28: VIGENTE
A29: 46118 | B29: ANGELA HILDA CANO RUDAS | C29: 30301760 | D29: BF287115 | E29: COLOMBIA | F29: CALDAS | G29: MANIZALES | H29: CLL 19 KR 39-10 | I29: 170004 | J29: canoangela302@gmail.com | K29: (+57) 3234756614 | L29: @angelacano | M29: 2Q+1V | N29: 100000 | O29: M17843664 | P29: NEQUI | Q29: JOHANA CASTAÑEDA | R29: ENVIADO | S29: VIGENTE
A30: 45817 | B30: ARGEMIRO BETANCUR OSORIO | C30: 9970468 | D30: AY548985 | E30: COLOMBIA | F30: RISARALDA | G30: DOSQUEBRADAS | H30: MZ 3 CASA 35 QUINTAS DE ARAGON | I30: 661001 | J30: argemirobetancur@gmail.com | K30: (+57) 3168072144 | L30: @Jrbetancur | M30: 10Q | N30: 200000 | O30: M15484172 | P30: NEQUI | Q30: JOHANA CASTAÑEDA | R30: ENVIADO | S30: VIGENTE
A31: 46014 | B31: ARGEMIRO BETANCUR OSORIO | C31: 9970468 | D31: AY548985 | E31: COLOMBIA | F31: RISARALDA | G31: DOSQUEBRADAS | H31: MZ 3 CASA 35 QUINTAS DE ARAGON | I31: 661001 | J31: argemirobetancur@gmail.com | K31: (+57) 3168072144 | L31: @Jrbetancur | M31: 4Q | N31: 100000 | O31: M20019425 | P31: NEQUI | Q31: JOHANA CASTAÑEDA | R31: ENVIADO | S31: VIGENTE
A32: 46053 | B32: ARGEMIRO BETANCUR OSORIO | C32: 9970468 | D32: AY548985 | E32: COLOMBIA | F32: RISARALDA | G32: DOSQUEBRADAS | H32: MZ 3 CASA 35 QUINTAS DE ARAGON | I32: 661001 | J32: argemirobetancur@gmail.com | K32: (+57) 3168072144 | L32: @Jrbetancur | M32: 6Q | N32: 150000 | O32: IFAK8SQYO3 | P32: BOLD | Q32: JOHANA CASTAÑEDA | R32: ENVIADO | S32: VIGENTE
A33: 46087 | B33: ARGEMIRO BETANCUR OSORIO | C33: 9970468 | D33: AY548985 | E33: COLOMBIA | F33: RISARALDA | G33: DOSQUEBRADAS | H33: MZ 3 CASA 35 QUINTAS DE ARAGON | I33: 661001 | J33: argemirobetancur@gmail.com | K33: (+57) 3168072144 | L33: @Jrbetancur | M33: 1ZIMCOIN+10Q | N33: 0 | O33: CAPACITACIONES | P33: N/A | Q33: JOHANA CASTAÑEDA | R33: ENVIADO | S33: VIGENTE
A34: 46109 | B34: ARGEMIRO BETANCUR OSORIO | C34: 9970468 | D34: AY548985 | E34: COLOMBIA | F34: RISARALDA | G34: DOSQUEBRADAS | H34: MZ 3 CASA 35 QUINTAS DE ARAGON | I34: 661001 | J34: argemirobetancur@gmail.com | K34: (+57) 3168072144 | L34: @Jrbetancur | M34: 2Q | N34: 100000 | O34: 10277706765592499727670027713162687 | P34: DAVIVIENDA | Q34: JOHANA CASTAÑEDA | R34: ENVIADO | S34: VIGENTE
A35: 46115 | B35: ARGEMIRO BETANCUR OSORIO | C35: 9970468 | D35: AY548985 | E35: COLOMBIA | F35: RISARALDA | G35: DOSQUEBRADAS | H35: MZ 3 CASA 35 QUINTAS DE ARAGON | I35: 661001 | J35: argemirobetancur@gmail.com | K35: (+57) 3168072144 | L35: @Jrbetancur | M35: 2Q+1V | N35: 100000 | O35: M04027622 | P35: NEQUI | Q35: JOHANA CASTAÑEDA | R35: ENVIADO | S35: VIGENTE
A36: 46123 | B36: ARGEMIRO BETANCUR OSORIO | C36: 9970468 | D36: AY548985 | E36: COLOMBIA | F36: RISARALDA | G36: DOSQUEBRADAS | H36: MZ 3 CASA 35 QUINTAS DE ARAGON | I36: 661001 | J36: argemirobetancur@gmail.com | K36: (+57) 3168072144 | L36: @Jrbetancur | M36: 6Q+6N | N36: 500000 | O36: M22551211 | P36: NEQUI | Q36: JOHANA CASTAÑEDA | R36: ENVIADO | S36: VIGENTE
A37: 46124.532 | B37: ARGEMIRO BETANCUR OSORIO | C37: 9970468 | D37: AY548985 | E37: COLOMBIA | F37: RISARALDA | G37: DOSQUEBRADAS | H37: MZ 3 CASA 35 QUINTAS DE ARAGON | I37: 661001 | J37: argemirobetancur@gmail.com | K37: (+57) 3168072144 | L37: @Jrbetancur | M37: 1N | N37: 0 | O37: GIRO RULETA | P37: N/A | Q37: JOHANA CASTAÑEDA | R37: ENVIADO | S37: VIGENTE
A38: 46150 | B38: ARGEMIRO BETANCUR OSORIO | C38: 9970468 | D38: AY548985 | E38: COLOMBIA | F38: RISARALDA | G38: DOSQUEBRADAS | H38: MZ 3 CASA 35 QUINTAS DE ARAGON | I38: 661001 | J38: argemirobetancur@gmail.com | K38: (+57) 3168072144 | L38: @Jrbetancur | M38: 2N | N38: 0 | O38: REFERIDOS | P38: N/A | Q38: JOHANA CASTAÑEDA | R38: ENVIADO | S38: VIGENTE
A39: 46172 | B39: ARGEMIRO BETANCUR OSORIO | C39: 9970468 | D39: AY548985 | E39: COLOMBIA | F39: RISARALDA | G39: DOSQUEBRADAS | H39: MANZANA 3 CASA 36 QUINTAS DE ARAGON PLAYA RICA | I39: 661001 | J39: argemirobetancur@gmail.com | K39: (+57) 3168072144 | L39: @Jrbetancur | M39: 5Q | N39: 100000 | O39: M12360461 | P39: LLAVE DAVIPLATA | Q39: JOHANA CASTAÑEDA | R39: ENVIADO | S39: VIGENTE
A40: 46232 | B40: ARGEMIRO BETANCUR OSORIO | C40: 9970468 | D40: AY548985 | E40: COLOMBIA | F40: RISARALDA | G40: DOSQUEBRADAS | H40: MANZANA 3 CASA 36 QUINTAS DE ARAGON PLAYA RICA | I40: 661001 | J40: argemirobetancur@gmail.com | K40: (+57) 3168072144 | L40: @Jrbetancur | M40: 10Q | N40: 200000 | O40: M23685554 | P40: NEQUI | Q40: JOHANA CASTAÑEDA | R40: ENVIADO | S40: VIGENTE
A41: 46255 | B41: ARGEMIRO BETANCUR OSORIO | C41: 9970468 | D41: AY548985 | E41: COLOMBIA | F41: RISARALDA | G41: DOSQUEBRADAS | H41: MANZANA 3 CASA 36 QUINTAS DE ARAGON PLAYA RICA | I41: 661001 | J41: argemirobetancur@gmail.com | K41: (+57) 3168072144 | L41: @Jrbetancur | M41: 9Q | N41: 180000 | O41: M04755586 | P41: NEQUI | Q41: JOHANA CASTAÑEDA | R41: ENVIADO | S41: VIGENTE
... A70: 46246 | B70: BLANCA LUCIA CASTRO GOMEZ | C70: 24246828 | D70: AW281157 | E70: COLOMBIA | F70: ARAUCA | G70: ARAUCA | H70: C 3 3 06 08 K 3 | I70: 816010 | J70: castrogomezlucia807@gmail.com | K70: (+57) 3508208562 | L70: QUINTILLION | M70: 1AGROCH | N70: 200000 | O70: M04737874 | P70: NEQUI | Q70: JOHANA CASTAÑEDA | R70: ENVIADO | S70: VIGENTE
A71: 46150 | B71: BYRON CABEZAS SALAZAR | C71: 8025220078 | D71: N/A | E71: ECUADOR | F71: ESMERALDAS | G71: ESMERALDAS | H71: RIO SUCIO | I71: 080101 | J71: cabezassalazarbyron@gmail.com | K71: (+593) 961837497 | L71: @byroncabezas | M71: 3Q+1V | N71: 30 | O71: 737-230-7921 | P71: WESTERN UNION | Q71: JOHANA CASTAÑEDA | R71: ENVIADO | S71: N/A
A72: 46150.438 | B72: BYRON CABEZAS SALAZAR | C72: 8025220078 | D72: N/A | E72: ECUADOR | F72: ESMERALDAS | G72: ESMERALDAS | H72: RIO SUCIO | I72: 080101 | J72: cabezassalazarbyron@gmail.com | K72: (+593) 961837497 | L72: @byroncabezas | M72: 2V | N72: 0 | O72: GIRO RULETA | P72: N/A | Q72: JOHANA CASTAÑEDA | R72: ENVIADO | S72: N/A
A73: 46150.438 | B73: BYRON CABEZAS SALAZAR | C73: 8025220078 | D73: N/A | E73: ECUADOR | F73: ESMERALDAS | G73: ESMERALDAS | H73: RIO SUCIO | I73: 080101 | J73: cabezassalazarbyron@gmail.com | K73: (+593) 961837497 | L73: @byroncabezas | M73: 3Q | N73: 60000 | O73: M08820920 | P73: NEQUI | Q73: JOHANA CASTAÑEDA | R73: ENVIADO | S73: N/A
A74: 45924 | B74: CARLOS ALEJANDRO FLOR TAQUEZ | C74: 1004773723 | D74: N/A | E74: COLOMBIA | F74: CAUCA | G74: POPAYAN | H74: CLL 58A N #11A - 16 | I74: 190001 | J74: cmlflor1995@gmail.com | K74: (+57) 3224726313 | L74: @alejoflort | M74: 1Q+1N+2V | N74: 200000 | O74: M21165569 | P74: NEQUI | Q74: JOHANA CASTAÑEDA | R74: ENVIADO | S74: N/A
A75: 45897 | B75: CARLOS FLOR CORDOBA | C75: 13079041 | D75: N/A | E75: COLOMBIA | F75: CAUCA | G75: POPAYAN | H75: LOTE N22 AIRES DE OCCIDENTE | I75: 190001 | J75: carlosmotacordoba@gmail.com | K75: (+57) 3122366361 | L75: @Carlosmot | M75: 2Q+3N+2V | N75: 300000 | O75: M10761937 | P75: NEQUI | Q75: JOHANA CASTAÑEDA | R75: ENVIADO | S75: N/A
A76: 45948.86 | B76: CARLOS HUBERTO GONZALEZ OCAMPO | C76: 75060017 | D76: N/A | E76: COLOMBIA | F76: CALDAS | G76: MANIZALES | H76: CLL 19 34 33 PSO 2 - EL CARMEN | I76: 170001 | J76: carloshubertogonzal@gmail.com | K76: (+57) 3113483457 | L76: Carlos Huberto Gonzalez Ocampo | M76: 2Q+3N | N76: 300000 | O76: M16426511 | P76: NEQUI | Q76: JOHANA CASTAÑEDA | R76: ENVIADO | S76: N/A
A77: 46055 | B77: CARLOS HUBERTO GONZALEZ OCAMPO | C77: 75060017 | D77: N/A | E77: COLOMBIA | F77: CALDAS | G77: MANIZALES | H77: CLL 19 34 33 PSO 2 - EL CARMEN | I77: 170001 | J77: carloshubertogonzal@gmail.com | K77: (+57) 3113483457 | L77: Carlos Huberto Gonzalez Ocampo | M77: 6Q | N77: 150000 | O77: 70292230 | P77: DAVIVIENDA | Q77: JOHANA CASTAÑEDA | R77: ENVIADO | S77: N/A
A78: 45885.57 | B78: CARMEN ADRIANA CASTAÑO CORREA | C78: 42085517 | D78: BF958098 | E78: COLOMBIA | F78: RISARALDA | G78: PEREIRA | H78: CASA 13 CONDOMINIO VILLAS DE TOLEDO SECTOR NUEVO SOL - MORELIA | I78: 660008 | J78: caradricasco123@gmail.com | K78: (+57) 3137205839 | L78: @Titacasco | M78: 2Q+2N | N78: 200000 | O78: 0000091157 | P78: BANCOLOMBIA | Q78: JOHANA CASTAÑEDA | R78: ENVIADO | S78: VIGENTE
A79: 45932 | B79: CARMEN ADRIANA CASTAÑO CORREA | C79: 42085517 | D79: BF958098 | E79: COLOMBIA | F79: RISARALDA | G79: PEREIRA | H79: CASA 13 CONDOMINIO VILLAS DE TOLEDO SECTOR NUEVO SOL - MORELIA | I79: 660008 | J79: caradricasco123@gmail.com | K79: (+57) 3137205839 | L79: @Titacasco | M79: 2Q | N79: 100000 | O79: 0000045561 | P79: BANCOLOMBIA | Q79: JOHANA CASTAÑEDA | R79: ENVIADO | S79: VIGENTE
A80: 45943 | B80: CARMEN ADRIANA CASTAÑO CORREA | C80: 42085517 | D80: BF958098 | E80: COLOMBIA | F80: RISARALDA | G80: PEREIRA | H80: CASA 13 CONDOMINIO VILLAS DE TOLEDO SECTOR NUEVO SOL - MORELIA | I80: 660008 | J80: caradricasco123@gmail.com | K80: (+57) 3137205839 | L80: @Titacasco | M80: COMODIN | N80: 100000 | O80: TRCİPZ3eRXEC | P80: BANCOLOMBIA | Q80: JOHANA CASTAÑEDA | R80: ENVIADO | S80: VIGENTE
A81: 46014 | B81: CARMEN ADRIANA CASTAÑO CORREA | C81: 42085517 | D81: BF958098 | E81: COLOMBIA | F81: RISARALDA | G81: PEREIRA | H81: CASA 13 CONDOMINIO VILLAS DE TOLEDO SECTOR NUEVO SOL - MORELIA | I81: 660008 | J81: caradricasco123@gmail.com | K81: (+57) 3137205839 | L81: @Titacasco | M81: 6Q+7N+2V | N81: 200000 | O81: TRZXkT5yBPEC | P81: BANCOLOMBIA | Q81: JOHANA CASTAÑEDA | R81: ENVIADO | S81: VIGENTE
A82: 46015 | B82: CARMEN ADRIANA CASTAÑO CORREA | C82: 42085517 | D82: BF958098 | E82: COLOMBIA | F82: RISARALDA | G82: PEREIRA | H82: CASA 13 CONDOMINIO VILLAS DE TOLEDO SECTOR NUEVO SOL - MORELIA | I82: 660008 | J82: caradricasco123@gmail.com | K82: (+57) 3137205839 | L82: @Titacasco | M82: // | N82: 100000 | O82: TRdSeOtQGyEC | P82: BANCOLOMBIA | Q82: JOHANA CASTAÑEDA | R82: ENVIADO | S82: VIGENTE
A83: 46022 | B83: CARMEN ADRIANA CASTAÑO CORREA | C83: 42085517 | D83: BF958098 | E83: COLOMBIA | F83: RISARALDA | G83: PEREIRA | H83: CASA 13 CONDOMINIO VILLAS DE TOLEDO SECTOR NUEVO SOL - MORELIA | I83: 660008 | J83: caradricasco123@gmail.com | K83: (+57) 3137205839 | L83: @Titacasco | M83: 2Q+2N | N83: 100000 | O83: TRjHOW5tHnEC | P83: BANCOLOMBIA | Q83: JOHANA CASTAÑEDA | R83: ENVIADO | S83: VIGENTE
A84: 46129 | B84: CARMEN ADRIANA CASTAÑO CORREA | C84: 42085517 | D84: BF958098 | E84: COLOMBIA | F84: RISARALDA | G84: PEREIRA | H84: CASA 13 CONDOMINIO VILLAS DE TOLEDO SECTOR NUEVO SOL - MORELIA | I84: 660008 | J84: caradricasco123@gmail.com | K84: (+57) 3137205839 | L84: @Titacasco | M84: 1V | N84: 0 | O84: GIRO RULETA | P84: N/A | Q84: JOHANA CASTAÑEDA | R84: ENVIADO | S84: VIGENTE
A85: 46129 | B85: CARMEN ADRIANA CASTAÑO CORREA | C85: 42085517 | D85: BF958098 | E85: COLOMBIA | F85: RISARALDA | G85: PEREIRA | H85: CASA 13 CONDOMINIO VILLAS DE TOLEDO SECTOR NUEVO SOL - MORELIA | I85: 660008 | J85: caradricasco123@gmail.com | K85: (+57) 3137205839 | L85: @Titacasco | M85: 2N | N85: 0 | O85: GIRO RULETA | P85: N/A | Q85: JOHANA CASTAÑEDA | R85: ENVIADO | S85: VIGENTE
... A87: 45966 | B87: CELSO NEL ORTEGA CAMPO | C87: 4612227 | D87: AX072151 | E87: COLOMBIA | F87: CAUCA | G87: POPAYAN | H87: VEREDA SANTA ROSA | I87: 190007 | J87: celsonelortegacampo@gmail.com | K87: (+57) 3177281238 | L87: @celsoortega | M87: 2Q | N87: 100000 | O87: 139563 | P87: REDEBAN | Q87: JOHANA CASTAÑEDA | R87: ENVIADO | S87: VIGENTE
A88: 46147 | B88: CHRISTIAN MARCO CARRERA OJEDA | C88: 48170952M | D88: PAK226890 | E88: ESPAÑA | F88: LA GARRIGA | G88: BARCELONA | H88: CARRERA, NOVA 91/3/2 | I88: 08530 | J88: christiankaratgold@gmail.com | K88: (+34)664826722 | L88: @Djchris77 | M88: 3Q+1V | N88: 100000 | O88: M18244264 | P88: NEQUI | Q88: JOHANA CASTAÑEDA | R88: ENVIADO | S88: VIGENTE
A89: 46148.421 | B89: CHRISTIAN MARCO CARRERA OJEDA | C89: 48170952M | D89: PAK226890 | E89: ESPAÑA | F89: LA GARRIGA | G89: BARCELONA | H89: CARRERA, NOVA 91/3/2 | I89: 08530 | J89: christiankaratgold@gmail.com | K89: (+34)664826722 | L89: @Djchris77 | M89: 1V | N89: 0 | O89: GIRO RULETA | P89: N/A | Q89: JOHANA CASTAÑEDA | R89: ENVIADO | S89: VIGENTE
A90: 45888.885 | B90: CLAUDIA CRISTINA CASTAÑO CORREA | C90: 42081364 | D90: AX201406 | E90: COLOMBIA | F90: RISARALDA | G90: PEREIRA | H90: ETP IV CSA 88 SAN JOSÉ DE LAS VILLAS SECTOR LOS PLANES- CERRITOS | I90: 660007 | J90: claudiacastanocorrea@gmail.com | K90: (+57) 3113581171 | L90: @claudiacas306 | M90: 6Q+5N+2V | N90: 200000 | O90: 0000093945 | P90: BANCOLOMBIA | Q90: JOHANA CASTAÑEDA | R90: ENVIADO | S90: VIGENTE
A91: 45932 | B91: CLAUDIA CRISTINA CASTAÑO CORREA | C91: 42081364 | D91: AX201406 | E91: COLOMBIA | F91: RISARALDA | G91: PEREIRA | H91: ETP IV CSA 88 SAN JOSÉ DE LAS VILLAS SECTOR LOS PLANES- CERRITOS | I91: 660007 | J91: claudiacastanocorrea@gmail.com | K91: (+57) 3113581171 | L91: @claudiacas306 | M91: 2Q+11N+2V | N91: 100000 | O91: 0000094806 | P91: BANCOLOMBIA | Q91: JOHANA CASTAÑEDA | R91: ENVIADO | S91: VIGENTE
A92: 45943 | B92: CLAUDIA CRISTINA CASTAÑO CORREA | C92: 42081364 | D92: AX201406 | E92: COLOMBIA | F92: RISARALDA | G92: PEREIRA | H92: ETP IV CSA 88 SAN JOSÉ DE LAS VILLAS SECTOR LOS PLANES- CERRITOS | I92: 660007 | J92: claudiacastanocorrea@gmail.com | K92: (+57) 3113581171 | L92: @claudiacas306 | M92: 2Q | N92: 100000 | O92: TRVidFL4anEC | P92: BANCOLOMBIA | Q92: JOHANA CASTAÑEDA | R92: ENVIADO | S92: VIGENTE
A93: 46014 | B93: CLAUDIA CRISTINA CASTAÑO CORREA | C93: 42081364 | D93: AX201406 | E93: COLOMBIA | F93: RISARALDA | G93: PEREIRA | H93: ETP IV CSA 88 SAN JOSÉ DE LAS VILLAS SECTOR LOS PLANES- CERRITOS | I93: 660007 | J93: claudiacastanocorrea@gmail.com | K93: (+57) 3113581171 | L93: @claudiacas306 | M93: COMODIN | N93: 200000 | O93: BAMJ1GY19H | P93: BANCOLOMBIA | Q93: JOHANA CASTAÑEDA | R93: ENVIADO | S93: VIGENTE
A94: 46022 | B94: CLAUDIA CRISTINA CASTAÑO CORREA | C94: 42081364 | D94: AX201406 | E94: COLOMBIA | F94: RISARALDA | G94: PEREIRA | H94: ETP IV CSA 88 SAN JOSÉ DE LAS VILLAS SECTOR LOS PLANES- CERRITOS | I94: 660007 | J94: claudiacastanocorrea@gmail.com | K94: (+57) 3113581171 | L94: @claudiacas306 | M94: COMODIN | N94: 300000 | O94: 3DGFE54NZ5 | P94: BANCOLOMBIA | Q94: JOHANA CASTAÑEDA | R94: ENVIADO | S94: VIGENTE
A95: 46055 | B95: CLAUDIA CRISTINA CASTAÑO CORREA | C95: 42081364 | D95: AX201406 | E95: COLOMBIA | F95: RISARALDA | G95: PEREIRA | H95: ETP IV CSA 88 SAN JOSÉ DE LAS VILLAS SECTOR LOS PLANES- CERRITOS | I95: 660007 | J95: claudiacastanocorrea@gmail.com | K95: (+57) 3113581171 | L95: @claudiacas306 | M95: 6Q | N95: 150000 | O95: SCZG2IAJD7 | P95: BANCOLOMBIA | Q95: JOHANA CASTAÑEDA | R95: ENVIADO | S95: VIGENTE
A96: 46125 | B96: CLAUDIA CRISTINA CASTAÑO CORREA | C96: 42081364 | D96: AX201406 | E96: COLOMBIA | F96: RISARALDA | G96: PEREIRA | H96: ETP IV CSA 88 SAN JOSÉ DE LAS VILLAS SECTOR LOS PLANES- CERRITOS | I96: 660007 | J96: claudiacastanocorrea@gmail.com | K96: (+57) 3113581171 | L96: @claudiacas306 | M96: 2Q | N96: 100000 | O96: KP5Z9B298P | P96: BANCOLOMBIA | Q96: JOHANA CASTAÑEDA | R96: ENVIADO | S96: VIGENTE
A97: 46125.47 | B97: CLAUDIA CRISTINA CASTAÑO CORREA | C97: 42081364 | D97: AX201406 | E97: COLOMBIA | F97: RISARALDA | G97: PEREIRA | H97: ETP IV CSA 88 SAN JOSÉ DE LAS VILLAS SECTOR LOS PLANES- CERRITOS | I97: 660007 | J97: claudiacastanocorrea@gmail.com | K97: (+57) 3113581171 | L97: @claudiacas306 | M97: 2V | N97: 0 | O97: GIRO RULETA | P97: N/A | Q97: JOHANA CASTAÑEDA | R97: ENVIADO | S97: VIGENTE
A98: 46129 | B98: CLAUDIA CRISTINA CASTAÑO CORREA | C98: 42081364 | D98: AX201406 | E98: COLOMBIA | F98: RISARALDA | G98: PEREIRA | H98: ETP IV CSA 88 SAN JOSÉ DE LAS VILLAS SECTOR LOS PLANES- CERRITOS | I98: 660007 | J98: claudiacastanocorrea@gmail.com | K98: (+57) 3113581171 | L98: @claudiacas306 | M98: 5Q+2N | N98: 200000 | O98: BDX118H5GM | P98: BANCOLOMBIA | Q98: JOHANA CASTAÑEDA | R98: ENVIADO | S98: VIGENTE
A99: 46130 | B99: CLAUDIA CRISTINA CASTAÑO CORREA | C99: 42081364 | D99: AX201406 | E99: COLOMBIA | F99: RISARALDA | G99: PEREIRA | H99: ETP IV CSA 88 SAN JOSÉ DE LAS VILLAS SECTOR LOS PLANES- CERRITOS | I99: 660007 | J99: claudiacastanocorrea@gmail.com | K99: (+57) 3113581171 | L99: @claudiacas306 | M99: 1Q | N99: 0 | O99: GIRO RULETA | P99: N/A | Q99: JOHANA CASTAÑEDA | R99: ENVIADO | S99: VIGENTE
A100: 46130 | B100: CLAUDIA CRISTINA CASTAÑO CORREA | C100: 42081364 | D100: AX201406 | E100: COLOMBIA | F100: RISARALDA | G100: PEREIRA | H100: ETP IV CSA 88 SAN JOSÉ DE LAS VILLAS SECTOR LOS PLANES- CERRITOS | I100: 660007 | J100: claudiacastanocorrea@gmail.com | K100: (+57) 3113581171 | L100: @claudiacas306 | M100: 1N | N100: 0 | O100: GIRO RULETA | P100: N/A | Q100: JOHANA CASTAÑEDA | R100: ENVIADO | S100: VIGENTE
A101: 45725.486 | B101: CLAUDIA ESTELA LOPEZ CAMACHO | C101: 34566045 | D101: AV514788 | E101: COLOMBIA | F101: CAUCA | G101: POPAYAN | H101: VEREDA CALIBIO DE POPAYAN | I101: 190008 | J101: clelopezca@gmail.com | K101: (+57) 3206863633 | L101: @clelopezca | M101: 1Q | N101: 100000 | O101: 0000096088 | P101: BANCOLOMBIA | Q101: JOHANA CASTAÑEDA | R101: ENVIADO | S101: VIGENTE
... A119: 45814.657 | B119: DELIA MARIA REY ACOSTA | C119: 40369286 | D119: AY186427 | E119: COLOMBIA | F119: META | G119: VILLAVICENCIO | H119: CALLE 32 N° 13 - 106 BARRIO LOS ROSALES / TORRE 3 APTO 301 CONJUNTO BARCELONA | I119: 500003 | J119: deliarey87@gmail.com | K119: (+57) 3134728208 | L119: @DeliaReyAcosta | M119: 5Q | N119: 120000 | O119: M10273096 | P119: NEQUI | Q119: JOHANA CASTAÑEDA | R119: ENVIADO | S119: VIGENTE
A120: 45856 | B120: DIANA MARCELA SANCHEZ MARIN | C120: 43872922 | D120: BA291405 | E120: COLOMBIA | F120: VALLE DEL CAUCA | G120: CARTAGO | H120: CRA 17 15 71 L6 MZ12 | I120: 762027 | J120: yayamarcelasm@hotmail.com | K120: (+57) 3218068881 | L120: SIN REGISTRO | M120: 4Q+4N+1ZIMBILL+1AGROCH | N120: 1500000 | O120: 0000092800 | P120: BANCOLOMBIA | Q120: JOHANA CASTAÑEDA | R120: ENVIADO | S120: VIGENTE
A121: 45834.847 | B121: DIANA PATRICIA ARBELAEZ FLOREZ | C121: 29832605 | D121: BA621141 | E121: COLOMBIA | F121: VALLE DEL CAUCA | G121: SEVILLA | H121: CR 48 60 26 MZ13C4 | I121: 762530 | J121: dianapatricia.arbelaezflorez@gmail.com | K121: (+57) 3112154756 | L121: @Daeiah | M121: 2Q | N121: 200000 | O121: 069692 | P121: REDEBAN | Q121: JOHANA CASTAÑEDA | R121: ENVIADO | S121: VIGENTE
A122: 45851 | B122: DIANA PATRICIA ARBELAEZ FLOREZ | C122: 29832605 | D122: BA621141 | E122: COLOMBIA | F122: VALLE DEL CAUCA | G122: SEVILLA | H122: CR 48 60 26 MZ13C4 | I122: 762530 | J122: dianapatricia.arbelaezflorez@gmail.com | K122: (+57) 3112154756 | L122: @Daeiah | M122: 1ZIMBILL | N122: 1000000 | O122: 20946 | P122: DAVIPLATA | Q122: JOHANA CASTAÑEDA | R122: ENVIADO | S122: VIGENTE
A123: 45856 | B123: DIANA PATRICIA ARBELAEZ FLOREZ | C123: 29832605 | D123: BA621141 | E123: COLOMBIA | F123: VALLE DEL CAUCA | G123: SEVILLA | H123: CR 48 60 26 MZ13C4 | I123: 762530 | J123: dianapatricia.arbelaezflorez@gmail.com | K123: (+57) 3112154756 | L123: @Daeiah | M123: 2Q+2N | N123: 200000 | O123: 0000090025 | P123: BANCOLOMBIA | Q123: JOHANA CASTAÑEDA | R123: ENVIADO | S123: VIGENTE
A124: 45907 | B124: DIANA PATRICIA ARBELAEZ FLOREZ | C124: 29832605 | D124: BA621141 | E124: COLOMBIA | F124: VALLE DEL CAUCA | G124: SEVILLA | H124: CR 48 60 26 MZ13C4 | I124: 762530 | J124: dianapatricia.arbelaezflorez@gmail.com | K124: (+57) 3112154756 | L124: @Daeiah | M124: 2Q+3N+5V | N124: 500000 | O124: 19561 | P124: DAVIPLATA | Q124: JOHANA CASTAÑEDA | R124: ENVIADO | S124: VIGENTE
A125: 45927 | B125: DIANA PATRICIA ARBELAEZ FLOREZ | C125: 29832605 | D125: BA621141 | E125: COLOMBIA | F125: VALLE DEL CAUCA | G125: SEVILLA | H125: CR 48 60 26 MZ13C4 | I125: 762530 | J125: dianapatricia.arbelaezflorez@gmail.com | K125: (+57) 3112154756 | L125: @Daeiah | M125: 2Q+3N+5V | N125: 500000 | O125: M19076408 | P125: NEQUI | Q125: JOHANA CASTAÑEDA | R125: ENVIADO | S125: VIGENTE
A126: 46111 | B126: DIANA PATRICIA ARBELAEZ FLOREZ | C126: 29832605 | D126: BA621141 | E126: COLOMBIA | F126: VALLE DEL CAUCA | G126: SEVILLA | H126: CR 48 60 26 MZ13C4 | I126: 762530 | J126: dianapatricia.arbelaezflorez@gmail.com | K126: (+57) 3112154756 | L126: @Daeiah | M126: 5Q+2N | N126: 200000 | O126: 42188 | P126: DAVIVIENDA | Q126: JOHANA CASTAÑEDA | R126: ENVIADO | S126: VIGENTE
A127: 46239 | B127: DIANA PATRICIA ARBELAEZ FLOREZ | C127: 29832605 | D127: BA621141 | E127: COLOMBIA | F127: VALLE DEL CAUCA | G127: SEVILLA | H127: CR 47D 60ASN 130 EL PINAR SEVILLA VALLE MANZ 13 | J127: dianapatricia.arbelaezflorez@gmail.com | K127: (+57) 3112154756 | L127: @Daeiah | M127: 5Q | N127: 100000 | O127: M04210962 | P127: NEQUI | Q127: JOHANA CASTAÑEDA | R127: ENVIADO | S127: VIGENTE
A128: 46280 | B128: DIANA PATRICIA ARBELAEZ FLOREZ | M128: 2Q+2N+2V | N128: 300000 | O128: 411140 | P128: DAVIPLATA | Q128: JOHANA CASTAÑEDA | R128: ENVIADO
A129: 45781 | B129: DIEGO FELIPE MAZORRA GUEVARA | C129: 10298946 | D129: N/A | E129: COLOMBIA | F129: CAUCA | G129: POPAYAN | H129: CRA 6 CLL 26AN-31 | I129: 190001 | J129: felipemazorra123@gmail.com | K129: (+57) 3045730698 | L129: @Pipemazorra | M129: 1Q | N129: 120000 | O129: 0000090317 | P129: BANCOLOMBIA | Q129: JOHANA CASTAÑEDA | R129: ENVIADO | S129: N/A
A130: 46053 | B130: DIEGO FELIPE MAZORRA GUEVARA | C130: 10298946 | D130: N/A | E130: COLOMBIA | F130: CAUCA | G130: POPAYAN | H130: CRA 6 CLL 26AN-31 | I130: 190001 | J130: felipemazorra123@gmail.com | K130: (+57) 3045730698 | L130: @Pipemazorra | M130: 1ZIMCOIN | N130: 500000 | O130: M21532276 | P130: NEQUI | Q130: JOHANA CASTAÑEDA | R130: ENVIADO | S130: N/A
A131: 45824 | B131: ELIAS SANABRIA MELGAREJO | C131: 13700726 | D131: BE134345 | E131: COLOMBIA | F131: SANTANDER | G131: CHARALA | H131: CARRERA 13 # 19 - 93 | I131: 682551 | J131: eliassanabriamelgarejo@gmail.com | K131: (+57) 3123154017 | L131: @gasasamel | M131: 10Q | N131: 200000 | O131: M11911834 | P131: NEQUI | Q131: JOHANA CASTAÑEDA | R131: ENVIADO | S131: VIGENTE
A132: 45828 | B132: ELIAS SANABRIA MELGAREJO | C132: 13700726 | D132: BE134345 | E132: COLOMBIA | F132: SANTANDER | G132: CHARALA | H132: CARRERA 13 # 19 - 93 | I132: 682551 | J132: eliassanabriamelgarejo@gmail.com | K132: (+57) 3123154017 | L132: @gasasamel | M132: 5Q | N132: 120000 | O132: M12499754 | P132: NEQUI | Q132: JOHANA CASTAÑEDA | R132: ENVIADO | S132: VIGENTE
A133: 46051 | B133: ELIAS SANABRIA MELGAREJO | C133: 13700726 | D133: BE134345 | E133: COLOMBIA | F133: SANTANDER | G133: CHARALA | H133: CARRERA 13 # 19 - 93 | I133: 682551 | J133: eliassanabriamelgarejo@gmail.com | K133: (+57) 3123154017 | L133: @gasasamel | M133: 6Q | N133: 150000 | O133: M14773681 | P133: NEQUI | Q133: JOHANA CASTAÑEDA | R133: ENVIADO | S133: VIGENTE
A134: 46128 | B134: ELIAS SANABRIA MELGAREJO | C134: 13700726 | D134: BE134345 | E134: COLOMBIA | F134: SANTANDER | G134: CHARALA | H134: CARRERA 13 # 19 - 93 | I134: 682551 | J134: eliassanabriamelgarejo@gmail.com | K134: (+57) 3123154017 | L134: @gasasamel | M134: 5Q+2N | N134: 200000 | O134: M17950556 | P134: NEQUI | Q134: JOHANA CASTAÑEDA | R134: ENVIADO | S134: VIGENTE
A135: 46128 | B135: ELIAS SANABRIA MELGAREJO | C135: 13700726 | D135: BE134345 | E135: COLOMBIA | F135: SANTANDER | G135: CHARALA | H135: CARRERA 13 # 19 - 93 | I135: 682551 | J135: eliassanabriamelgarejo@gmail.com | K135: (+57) 3123154017 | L135: @gasasamel | M135: 1Q | N135: 0 | O135: GIRO RULETA | P135: N/A | Q135: JOHANA CASTAÑEDA | R135: ENVIADO | S135: VIGENTE
A136: 46128 | B136: ELIAS SANABRIA MELGAREJO | C136: 13700726 | D136: BE134345 | E136: COLOMBIA | F136: SANTANDER | G136: CHARALA | H136: CARRERA 13 # 19 - 93 | I136: 682551 | J136: eliassanabriamelgarejo@gmail.com | K136: (+57) 3123154017 | L136: @gasasamel | M136: 1V | N136: 0 | O136: GIRO RULETA | P136: N/A | Q136: JOHANA CASTAÑEDA | R136: ENVIADO | S136: VIGENTE
A137: 45846 | B137: ELSA PATRICIA MARULANDA GIRALDO | C137: 30332751 | D137: AV404654 | E137: COLOMBIA | F137: CALDAS | G137: MANIZALES | H137: CARRERA 19A 4A2-21 CASA 15 | I137: 170001 | J137: elsa_0626@hotmail.com | K137: (+57) 3113546107 | L137: @rubelio24 | M137: 4Q+3N | N137: 300000 | O137: M9223495 | P137: NEQUI BOUCHER COMPARTIDO | Q137: JOHANA CASTAÑEDA | R137: ENVIADO | S137: VIGENTE
A138: 46003 | B138: EMILSEN YANGANA OLIVAR | C138: 34553021 | D138: N/A | E138: COLOMBIA | F138: CALDAS | G138: LA DORADA | H138: LOTE 8 MANZANA 0 VILLA ESPERANZA | I138: 175030 | J138: emita021@gmail.com | K138: (+57) 3163275130 | L138: @EmilsenYang | M138: 2Q | N138: 100000 | O138: M13018057 | P138: NEQUI | Q138: JOHANA CASTAÑEDA | R138: ENVIADO | S138: N/A
A139: 46053 | B139: EMILSEN YANGANA OLIVAR | C139: 34553021 | D139: N/A | E139: COLOMBIA | F139: CALDAS | G139: LA DORADA | H139: LOTE 8 MANZANA 0 VILLA ESPERANZA | I139: 175030 | J139: emita021@gmail.com | K139: (+57) 3163275130 | L139: @EmilsenYang | M139: 6Q | N139: 150000 | O139: M09540911 | P139: NEQUI | Q139: JOHANA CASTAÑEDA | R139: ENVIADO | S139: N/A
A140: 46109 | B140: EMILSEN YANGANA OLIVAR | C140: 34553021 | D140: N/A | E140: COLOMBIA | F140: CALDAS | G140: LA DORADA | H140: LOTE 8 MANZANA 0 VILLA ESPERANZA | I140: 175030 | J140: emita021@gmail.com | K140: (+57) 3163275130 | L140: @EmilsenYang | M140: 2Q | N140: 100000 | O140: M02071647 | P140: NEQUI | Q140: JOHANA CASTAÑEDA | R140: ENVIADO | S140: N/A
A141: 46237 | B141: EMILSEN YANGANA OLIVAR | C141: 34553021 | D141: N/A | E141: COLOMBIA | F141: CALDAS | G141: LA DORADA | H141: LOTE 8 MANZANA 0 VILLA ESPERANZA | I141: 175030 | J141: emita021@gmail.com | K141: (+57) 3163275130 | L141: @EmilsenYang | M141: 3Q | N141: 60000 | O141: M04210962 | P141: NEQUI | Q141: JOHANA CASTAÑEDA | R141: ENVIADO | S141: N/A
A142: 46279 | B142: EMILSEN YANGANA OLIVAR | C142: 34553021 | D142: N/A | E142: COLOMBIA | F142: CALDAS | G142: LA DORADA | H142: LOTE 8 MANZANA 0 VILLA ESPERANZA | I142: 175030 | J142: emita021@gmail.com | K142: (+57) 3163275130 | L142: @EmilsenYang | M142: 3Q | N142: CAJA | O142: M0746420 | P142: NEQUI | Q142: JOHANA CASTAÑEDA | R142: ENVIADO | S142: N/A
A143: 45836 | B143: ERICKA YAMILE VALENCIA GOMEZ | C143: 43793721 | D143: BG508095 | E143: COLOMBIA | F143: ANTIOQUIA | G143: GUARNE | H143: CRA. 50 # 63-16 | I143: 054050 | J143: evalencia6445@gmail.com | K143: (+57) 3114291925 | L143: @Ericka_valencia | M143: 4Q | N143: 500000 | O143: M10992188 | P143: NEQUI | Q143: JOHANA CASTAÑEDA | R143: ENVIADO | S143: VIGENTE
A144: 45946 | B144: ERICKA YAMILE VALENCIA GOMEZ | C144: 43793721 | D144: BG508095 | E144: COLOMBIA | F144: ANTIOQUIA | G144: GUARNE | H144: CRA. 50 # 63-16 | I144: 054050 | J144: evalencia6445@gmail.com | K144: (+57) 3114291925 | L144: @Ericka_valencia | M144: COMODIN | N144: 200000 | O144: 0000048720 | P144: BANCOLOMBIA | Q144: JOHANA CASTAÑEDA | R144: ENVIADO | S144: VIGENTE
A145: 46014 | B145: ERICKA YAMILE VALENCIA GOMEZ | C145: 43793721 | D145: BG508095 | E145: COLOMBIA | F145: ANTIOQUIA | G145: GUARNE | H145: CRA. 50 # 63-16 | I145: 054050 | J145: evalencia6445@gmail.com | K145: (+57) 3114291925 | L145: @Ericka_valencia | M145: 4Q+5N+2V | N145: 200000 | O145: TQTBBLR4L5 | P145: BANCOLOMBIA | Q145: JOHANA CASTAÑEDA | R145: ENVIADO | S145: VIGENTE
A146: 46175 | B146: ERICKA YAMILE VALENCIA GOMEZ | C146: 43793721 | D146: BG508095 | E146: COLOMBIA | F146: ANTIOQUIA | G146: GUARNE | H146: CRA. 50 # 63-16 | I146: 054050 | J146: evalencia6445@gmail.com | K146: (+57) 3114291925 | L146: @Ericka_valencia | M146: 3ZIMCOIN | N146: 1000000 | O146: CNX90P1D8A | P146: BANCOLOMBIA | Q146: JOHANA CASTAÑEDA | R146: ENVIADO | S146: VIGENTE
...

Sheet MATRIZ LISTADO
V3: SI | W3: FIDUCIA
V4: NO | W4: NUBE
C16: LIDER: | D16: JOHANA CASTAÑEDA
B18: CC-ID-DNI | C18: NOMBRE | D18: QUINTILLION 5M | F18: NONGENTILLION 10M | H18: VIGINTILLION 7,5M | J18: MONEDA ZIMBABWE 500k | L18: BILLETE DE ZIMBABWE 12,5M | N18: AGROCHEQUE50M | P18: OTROS | R18: USD | S18: TOTAL -10% | T18: 1% PAGO INICIAL | U18: FIDUCIA | V18: NUBE | W18: SKR SI/NO | X18: FIDUCIA/NUBE | Y18: PORCENTAJES | AB18: TOTAL
A19: LISTA | B19: CC-ID-DNI | C19: NOMBRE | D19: CANT | E19: MONTO | F19: CANT2 | G19: MONTO2 | H19: CANT3 | I19: MONTO3 | J19: CANT4 | K19: MONTO4 | L19: CANT5 | M19: MONTO5 | N19: CANT6 | O19: MONTO6 | P19: CANT7 | Q19: MONTO7 | R19: USD | S19: TOTAL -10% | T19: 1% PAGO INICIAL | U19: % FIDUCIA | V19: % NUBE | W19: SKR SI/NO | X19: FIDUCIA/NUBE | Y19: BANCO | Z19: FIDUCIA | AA19: NUBE | AB19: 100%
A20: 1 | B20: 1088244700 | C20: ALEJANDRA GALLEGO RAMÍREZ | D20: 1 | E20: =(Tabla3[[#This Row],[CANT]]*5000000) -> 5000000 | F20: 1 | G20: =(Tabla3[[#This Row],[CANT2]]*10000000) -> 10000000 | H20: 2 | I20: =(Tabla3[[#This Row],[CANT3]]*7500000) -> 15000000 | R20: =(Tabla3[[#This Row],[MONTO]]+Tabla3[[#This Row],[MONTO2]]+Tabla3[[#This Row],[MONTO3]]+Tabla3[[#This Row],[MONTO4]]+Tabla3[[#This Row],[MONTO5]]+Tabla3[[#This Row],[MONTO6]]+Tabla3[[#This Row],[MONTO7]]) -> 30000000 | S20: =R20-(R20*10%) -> 27000000 | T20: =(S20*1%) -> 270000 | U20: =(Tabla3[[#This Row],[TOTAL -10%]]*Tabla3[[#This Row],[FIDUCIA]]) -> 26730000 | V20: =(Tabla3[[#This Row],[TOTAL -10%]]*Tabla3[[#This Row],[NUBE]]) -> 0 | W20: SI | X20: FIDUCIA | Y20: 0.01 | Z20: 0.99 | AB20: =SUM(Y20:AA20) -> 1 | AC20: =IF(AB20="","",IF(AB20=100%,"OK","ERROR")) -> OK
A21: =(A20+1) -> 2 | B21: 25235412 | C21: ALEJANDRA MARIA BETANCUR OSORIO | D21: 2 | E21: =(Tabla3[[#This Row],[CANT]]*5000000) -> 10000000 | H21: 1 | I21: =(Tabla3[[#This Row],[CANT3]]*7500000) -> 7500000 | R21: =(Tabla3[[#This Row],[MONTO]]+Tabla3[[#This Row],[MONTO2]]+Tabla3[[#This Row],[MONTO3]]+Tabla3[[#This Row],[MONTO4]]+Tabla3[[#This Row],[MONTO5]]+Tabla3[[#This Row],[MONTO6]]+Tabla3[[#This Row],[MONTO7]]) -> 17500000 | S21: =R21-(R21*10%) -> 15750000 | T21: =(S21*1%) -> 157500 | U21: =(Tabla3[[#This Row],[TOTAL -10%]]*Tabla3[[#This Row],[FIDUCIA]]) -> 15592500 | V21: =(Tabla3[[#This Row],[TOTAL -10%]]*Tabla3[[#This Row],[NUBE]]) -> 0 | W21: SI | X21: FIDUCIA | Y21: 0.01 | Z21: 0.99 | AB21: =SUM(Y21:AA21) -> 1 | AC21: =IF(AB21="","",IF(AB21=100%,"OK","ERROR")) -> OK
A22: =(A21+1) -> 3 | B22: 10018741 | C22: ALEXANDER MARIN CASTAÑEDA | D22: 63 | E22: =(Tabla3[[#This Row],[CANT]]*5000000) -> 315000000 | F22: 10 | G22: =(Tabla3[[#This Row],[CANT2]]*10000000) -> 100000000 | H22: 4 | I22: =(Tabla3[[#This Row],[CANT3]]*7500000) -> 30000000 | J22: 1 | K22: =(Tabla3[[#This Row],[CANT4]]*500000) -> 500000 | R22: =(Tabla3[[#This Row],[MONTO]]+Tabla3[[#This Row],[MONTO2]]+Tabla3[[#This Row],[MONTO3]]+Tabla3[[#This Row],[MONTO4]]+Tabla3[[#This Row],[MONTO5]]+Tabla3[[#This Row],[MONTO6]]+Tabla3[[#This Row],[MONTO7]]) -> 445500000 | S22: =R22-(R22*10%) -> 400950000 | T22: =(S22*1%) -> 4009500 | U22: =(Tabla3[[#This Row],[TOTAL -10%]]*Tabla3[[#This Row],[FIDUCIA]]) -> 0 | V22: =(Tabla3[[#This Row],[TOTAL -10%]]*Tabla3[[#This Row],[NUBE]]) -> 396940500 | W22: SI | X22: NUBE | Y22: 0.01 | AA22: 0.99 | AB22: =SUM(Y22:AA22) -> 1 | AC22: =IF(AB22="","",IF(AB22=100%,"OK","ERROR")) -> OK
A23: =(A22+1) -> 4 | B23: 55179153 | C23: ALIDA FRANCY OVIEDO LOZADA | D23: 10 | E23: =(Tabla3[[#This Row],[CANT]]*5000000) -> 50000000 | F23: 5 | G23: =(Tabla3[[#This Row],[CANT2]]*10000000) -> 50000000 | H23: 2 | I23: =(Tabla3[[#This Row],[CANT3]]*7500000) -> 15000000 | R23: =(Tabla3[[#This Row],[MONTO]]+Tabla3[[#This Row],[MONTO2]]+Tabla3[[#This Row],[MONTO3]]+Tabla3[[#This Row],[MONTO4]]+Tabla3[[#This Row],[MONTO5]]+Tabla3[[#This Row],[MONTO6]]+Tabla3[[#This Row],[MONTO7]]) -> 115000000 | S23: =R23-(R23*10%) -> 103500000 | T23: =(S23*1%) -> 1035000 | U23: =(Tabla3[[#This Row],[TOTAL -10%]]*Tabla3[[#This Row],[FIDUCIA]]) -> 0 | V23: =(Tabla3[[#This Row],[TOTAL -10%]]*Tabla3[[#This Row],[NUBE]]) -> 102465000 | W23: SI | X23: NUBE | Y23: 0.01 | AA23: 0.99 | AB23: =SUM(Y23:AA23) -> 1 | AC23: =IF(AB23="","",IF(AB23=100%,"OK","ERROR")) -> OK
A24: =(A23+1) -> 5 | B24: 7148008 | C24: ANA BEATRIZ CARIAS PINO | D24: 3 | E24: =(Tabla3[[#This Row],[CANT]]*5000000) -> 15000000 | R24: =(Tabla3[[#This Row],[MONTO]]+Tabla3[[#This Row],[MONTO2]]+Tabla3[[#This Row],[MONTO3]]+Tabla3[[#This Row],[MONTO4]]+Tabla3[[#This Row],[MONTO5]]+Tabla3[[#This Row],[MONTO6]]+Tabla3[[#This Row],[MONTO7]]) -> 15000000 | S24: =R24-(R24*10%) -> 13500000 | T24: =(S24*1%) -> 135000 | U24: =(Tabla3[[#This Row],[TOTAL -10%]]*Tabla3[[#This Row],[FIDUCIA]]) -> 13365000 | V24: =(Tabla3[[#This Row],[TOTAL -10%]]*Tabla3[[#This Row],[NUBE]]) -> 0 | W24: SI | X24: FIDUCIA | Y24: 0.01 | Z24: 0.99 | AB24: =SUM(Y24:AA24) -> 1 | AC24: =IF(AB24="","",IF(AB24=100%,"OK","ERROR")) -> OK
A25: =(A24+1) -> 6 | B25: 41927246 | C25: ANA ISABEL VALENCIA MESA | D25: 5 | E25: =(Tabla3[[#This Row],[CANT]]*5000000) -> 25000000 | R25: =(Tabla3[[#This Row],[MONTO]]+Tabla3[[#This Row],[MONTO2]]+Tabla3[[#This Row],[MONTO3]]+Tabla3[[#This Row],[MONTO4]]+Tabla3[[#This Row],[MONTO5]]+Tabla3[[#This Row],[MONTO6]]+Tabla3[[#This Row],[MONTO7]]) -> 25000000 | S25: =R25-(R25*10%) -> 22500000 | T25: =(S25*1%) -> 225000 | U25: =(Tabla3[[#This Row],[TOTAL -10%]]*Tabla3[[#This Row],[FIDUCIA]]) -> 0 | V25: =(Tabla3[[#This Row],[TOTAL -10%]]*Tabla3[[#This Row],[NUBE]]) -> 22275000 | W25: SI | X25: NUBE | Y25: 0.01 | AA25: 0.99 | AB25: =SUM(Y25:AA25) -> 1 | AC25: =IF(AB25="","",IF(AB25=100%,"OK","ERROR")) -> OK
A26: =(A25+1) -> 7 | B26: 24587181 | C26: ANAYIBER CARVAJAL CESPEDES | D26: 2 | E26: =(Tabla3[[#This Row],[CANT]]*5000000) -> 10000000 | F26: 2 | G26: =(Tabla3[[#This Row],[CANT2]]*10000000) -> 20000000 | R26: =(Tabla3[[#This Row],[MONTO]]+Tabla3[[#This Row],[MONTO2]]+Tabla3[[#This Row],[MONTO3]]+Tabla3[[#This Row],[MONTO4]]+Tabla3[[#This Row],[MONTO5]]+Tabla3[[#This Row],[MONTO6]]+Tabla3[[#This Row],[MONTO7]]) -> 30000000 | S26: =R26-(R26*10%) -> 27000000 | T26: =(S26*1%) -> 270000 | U26: =(Tabla3[[#This Row],[TOTAL -10%]]*Tabla3[[#This Row],[FIDUCIA]]) -> 0 | V26: =(Tabla3[[#This Row],[TOTAL -10%]]*Tabla3[[#This Row],[NUBE]]) -> 26730000 | W26: SI | X26: NUBE | Y26: 0.01 | AA26: 0.99 | AB26: =SUM(Y26:AA26) -> 1 | AC26: =IF(AB26="","",IF(AB26=100%,"OK","ERROR")) -> OK
A27: =(A26+1) -> 8 | B27: 75070176 | C27: ANDRES MAURICIO MURILLO BALLESTEROS | D27: 2 | E27: =(Tabla3[[#This Row],[CANT]]*5000000) -> 10000000 | F27: 3 | G27: =(Tabla3[[#This Row],[CANT2]]*10000000) -> 30000000 | R27: =(Tabla3[[#This Row],[MONTO]]+Tabla3[[#This Row],[MONTO2]]+Tabla3[[#This Row],[MONTO3]]+Tabla3[[#This Row],[MONTO4]]+Tabla3[[#This Row],[MONTO5]]+Tabla3[[#This Row],[MONTO6]]+Tabla3[[#This Row],[MONTO7]]) -> 40000000 | S27: =R27-(R27*10%) -> 36000000 | T27: =(S27*1%) -> 360000 | U27: =(Tabla3[[#This Row],[TOTAL -10%]]*Tabla3[[#This Row],[FIDUCIA]]) -> 35640000 | V27: =(Tabla3[[#This Row],[TOTAL -10%]]*Tabla3[[#This Row],[NUBE]]) -> 0 | W27: SI | X27: FIDUCIA | Y27: 0.01 | Z27: 0.99 | AB27: =SUM(Y27:AA27) -> 1 | AC27: =IF(AB27="","",IF(AB27=100%,"OK","ERROR")) -> OK
A28: =(A27+1) -> 9 | B28: 1802036838 | C28: ANGEL ALCIDES PAZMIÑO VASCONEZ | D28: 2 | E28: =(Tabla3[[#This Row],[CANT]]*5000000) -> 10000000 | R28: =(Tabla3[[#This Row],[MONTO]]+Tabla3[[#This Row],[MONTO2]]+Tabla3[[#This Row],[MONTO3]]+Tabla3[[#This Row],[MONTO4]]+Tabla3[[#This Row],[MONTO5]]+Tabla3[[#This Row],[MONTO6]]+Tabla3[[#This Row],[MONTO7]]) -> 10000000 | S28: =R28-(R28*10%) -> 9000000 | T28: =(S28*1%) -> 90000 | U28: =(Tabla3[[#This Row],[TOTAL -10%]]*Tabla3[[#This Row],[FIDUCIA]]) -> 0 | V28: =(Tabla3[[#This Row],[TOTAL -10%]]*Tabla3[[#This Row],[NUBE]]) -> 8910000 | W28: SI | X28: NUBE | Y28: 0.01 | AA28: 0.99 | AB28: =SUM(Y28:AA28) -> 1 | AC28: =IF(AB28="","",IF(AB28=100%,"OK","ERROR")) -> OK
A29: =(A28+1) -> 10 | B29: 98146902 | C29: ANGEL RAMIRO TRUJILLO TRUJILLO | D29: 11 | E29: =(Tabla3[[#This Row],[CANT]]*5000000) -> 55000000 | F29: 2 | G29: =(Tabla3[[#This Row],[CANT2]]*10000000) -> 20000000 | R29: =(Tabla3[[#This Row],[MONTO]]+Tabla3[[#This Row],[MONTO2]]+Tabla3[[#This Row],[MONTO3]]+Tabla3[[#This Row],[MONTO4]]+Tabla3[[#This Row],[MONTO5]]+Tabla3[[#This Row],[MONTO6]]+Tabla3[[#This Row],[MONTO7]]) -> 75000000 | S29: =R29-(R29*10%) -> 67500000 | T29: =(S29*1%) -> 675000 | U29: =(Tabla3[[#This Row],[TOTAL -10%]]*Tabla3[[#This Row],[FIDUCIA]]) -> 0 | V29: =(Tabla3[[#This Row],[TOTAL -10%]]*Tabla3[[#This Row],[NUBE]]) -> 66825000 | W29: SI | X29: FIDUCIA | Y29: 0.01 | AA29: 0.99 | AB29: =SUM(Y29:AA29) -> 1 | AC29: =IF(AB29="","",IF(AB29=100%,"OK","ERROR")) -> OK
A30: =(A28+1) -> 10 | B30: 30301760 | C30: ANGELA HILDA CANO RUDAS | D30: 12 | E30: =(Tabla3[[#This Row],[CANT]]*5000000) -> 60000000 | H30: 1 | I30: =(Tabla3[[#This Row],[CANT3]]*7500000) -> 7500000 | R30: =(Tabla3[[#This Row],[MONTO]]+Tabla3[[#This Row],[MONTO2]]+Tabla3[[#This Row],[MONTO3]]+Tabla3[[#This Row],[MONTO4]]+Tabla3[[#This Row],[MONTO5]]+Tabla3[[#This Row],[MONTO6]]+Tabla3[[#This Row],[MONTO7]]) -> 67500000 | S30: =R30-(R30*10%) -> 60750000 | T30: =(S30*1%) -> 607500 | U30: =(Tabla3[[#This Row],[TOTAL -10%]]*Tabla3[[#This Row],[FIDUCIA]]) -> 0 | V30: =(Tabla3[[#This Row],[TOTAL -10%]]*Tabla3[[#This Row],[NUBE]]) -> 60142500 | W30: SI | X30: NUBE | Y30: 0.01 | AA30: 0.99 | AB30: =SUM(Y30:AA30) -> 1 | AC30: =IF(AB30="","",IF(AB30=100%,"OK","ERROR")) -> OK
A31: =(A30+1) -> 11 | B31: 9970468 | C31: ARGEMIRO BETANCUR OSORIO | D31: 64 | E31: =(Tabla3[[#This Row],[CANT]]*5000000) -> 320000000 | F31: 8 | G31: =(Tabla3[[#This Row],[CANT2]]*10000000) -> 80000000 | H31: 1 | I31: =(Tabla3[[#This Row],[CANT3]]*7500000) -> 7500000 | J31: 1 | K31: =(Tabla3[[#This Row],[CANT4]]*500000) -> 500000 | R31: =(Tabla3[[#This Row],[MONTO]]+Tabla3[[#This Row],[MONTO2]]+Tabla3[[#This Row],[MONTO3]]+Tabla3[[#This Row],[MONTO4]]+Tabla3[[#This Row],[MONTO5]]+Tabla3[[#This Row],[MONTO6]]+Tabla3[[#This Row],[MONTO7]]) -> 408000000 | S31: =R31-(R31*10%) -> 367200000 | T31: =(S31*1%) -> 3672000 | U31: =(Tabla3[[#This Row],[TOTAL -10%]]*Tabla3[[#This Row],[FIDUCIA]]) -> 0 | V31: =(Tabla3[[#This Row],[TOTAL -10%]]*Tabla3[[#This Row],[NUBE]]) -> 363528000 | W31: SI | X31: NUBE | Y31: 0.01 | AA31: 0.99 | AB31: =SUM(Y31:AA31) -> 1 | AC31: =IF(AB31="","",IF(AB31=100%,"OK","ERROR")) -> OK
A32: =(A31+1) -> 12 | B32: 10276687 | C32: BELMER AUGUSTO BETANCUR OSORIO | D32: 20 | E32: =(Tabla3[[#This Row],[CANT]]*5000000) -> 100000000 | F32: 9 | G32: =(Tabla3[[#This Row],[CANT2]]*10000000) -> 90000000 | H32: 5 | I32: =(Tabla3[[#This Row],[CANT3]]*7500000) -> 37500000 | R32: =(Tabla3[[#This Row],[MONTO]]+Tabla3[[#This Row],[MONTO2]]+Tabla3[[#This Row],[MONTO3]]+Tabla3[[#This Row],[MONTO4]]+Tabla3[[#This Row],[MONTO5]]+Tabla3[[#This Row],[MONTO6]]+Tabla3[[#This Row],[MONTO7]]) -> 227500000 | S32: =R32-(R32*10%) -> 204750000 | T32: =(S32*1%) -> 2047500 | U32: =(Tabla3[[#This Row],[TOTAL -10%]]*Tabla3[[#This Row],[FIDUCIA]]) -> 202702500 | V32: =(Tabla3[[#This Row],[TOTAL -10%]]*Tabla3[[#This Row],[NUBE]]) -> 0 | W32: SI | X32: FIDUCIA | Y32: 0.01 | Z32: 0.99 | AB32: =SUM(Y32:AA32) -> 1 | AC32: =IF(AB32="","",IF(AB32=100%,"OK","ERROR")) -> OK
A33: =(A32+1) -> 13 | B33: 24246828 | C33: BLANCA LUCIA CASTRO GOMEZ | D33: 99 | E33: =(Tabla3[[#This Row],[CANT]]*5000000) -> 495000000 | F33: 16 | G33: =(Tabla3[[#This Row],[CANT2]]*10000000) -> 160000000 | H33: 9 | I33: =(Tabla3[[#This Row],[CANT3]]*7500000) -> 67500000 | J33: 2 | K33: =(Tabla3[[#This Row],[CANT4]]*500000) -> 1000000 | N33: 1 | O33: =(Tabla3[[#This Row],[CANT6]]*200000) -> 200000 | R33: =(Tabla3[[#This Row],[MONTO]]+Tabla3[[#This Row],[MONTO2]]+Tabla3[[#This Row],[MONTO3]]+Tabla3[[#This Row],[MONTO4]]+Tabla3[[#This Row],[MONTO5]]+Tabla3[[#This Row],[MONTO6]]+Tabla3[[#This Row],[MONTO7]]) -> 723700000 | S33: =R33-(R33*10%) -> 651330000 | T33: =(S33*1%) -> 6513300 | U33: =(Tabla3[[#This Row],[TOTAL -10%]]*Tabla3[[#This Row],[FIDUCIA]]) -> 0 | V33: =(Tabla3[[#This Row],[TOTAL -10%]]*Tabla3[[#This Row],[NUBE]]) -> 644816700 | W33: SI | X33: NUBE | Y33: 0.01 | AA33: 0.99 | AB33: =SUM(Y33:AA33) -> 1 | AC33: =IF(AB33="","",IF(AB33=100%,"OK","ERROR")) -> OK
A34: =(A33+1) -> 14 | B34: 1004773723 | C34: CARLOS ALEJANDRO FLOR TAQUEZ | D34: 1 | E34: =(Tabla3[[#This Row],[CANT]]*5000000) -> 5000000 | F34: 1 | G34: =(Tabla3[[#This Row],[CANT2]]*10000000) -> 10000000 | H34: 2 | I34: =(Tabla3[[#This Row],[CANT3]]*7500000) -> 15000000 | R34: =(Tabla3[[#This Row],[MONTO]]+Tabla3[[#This Row],[MONTO2]]+Tabla3[[#This Row],[MONTO3]]+Tabla3[[#This Row],[MONTO4]]+Tabla3[[#This Row],[MONTO5]]+Tabla3[[#This Row],[MONTO6]]+Tabla3[[#This Row],[MONTO7]]) -> 30000000 | S34: =R34-(R34*10%) -> 27000000 | T34: =(S34*1%) -> 270000 | U34: =(Tabla3[[#This Row],[TOTAL -10%]]*Tabla3[[#This Row],[FIDUCIA]]) -> 26730000 | V34: =(Tabla3[[#This Row],[TOTAL -10%]]*Tabla3[[#This Row],[NUBE]]) -> 0 | W34: SI | X34: FIDUCIA | Y34: 0.01 | Z34: 0.99 | AB34: =SUM(Y34:AA34) -> 1 | AC34: =IF(AB34="","",IF(AB34=100%,"OK","ERROR")) -> OK
A35: =(A34+1) -> 15 | B35: 13079041 | C35: CARLOS FLOR CORDOBA | D35: 2 | E35: =(Tabla3[[#This Row],[CANT]]*5000000) -> 10000000 | F35: 3 | G35: =(Tabla3[[#This Row],[CANT2]]*10000000) -> 30000000 | H35: 2 | I35: =(Tabla3[[#This Row],[CANT3]]*7500000) -> 15000000 | R35: =(Tabla3[[#This Row],[MONTO]]+Tabla3[[#This Row],[MONTO2]]+Tabla3[[#This Row],[MONTO3]]+Tabla3[[#This Row],[MONTO4]]+Tabla3[[#This Row],[MONTO5]]+Tabla3[[#This Row],[MONTO6]]+Tabla3[[#This Row],[MONTO7]]) -> 55000000 | S35: =R35-(R35*10%) -> 49500000 | T35: =(S35*1%) -> 495000 | U35: =(Tabla3[[#This Row],[TOTAL -10%]]*Tabla3[[#This Row],[FIDUCIA]]) -> 49005000 | V35: =(Tabla3[[#This Row],[TOTAL -10%]]*Tabla3[[#This Row],[NUBE]]) -> 0 | W35: SI | X35: FIDUCIA | Y35: 0.01 | Z35: 0.99 | AB35: =SUM(Y35:AA35) -> 1 | AC35: =IF(AB35="","",IF(AB35=100%,"OK","ERROR")) -> OK
A36: =(A35+1) -> 16 | B36: 75060017 | C36: CARLOS HUBERTO GONZALEZ OCAMPO | D36: 8 | E36: =(Tabla3[[#This Row],[CANT]]*5000000) -> 40000000 | F36: 3 | G36: =(Tabla3[[#This Row],[CANT2]]*10000000) -> 30000000 | R36: =(Tabla3[[#This Row],[MONTO]]+Tabla3[[#This Row],[MONTO2]]+Tabla3[[#This Row],[MONTO3]]+Tabla3[[#This Row],[MONTO4]]+Tabla3[[#This Row],[MONTO5]]+Tabla3[[#This Row],[MONTO6]]+Tabla3[[#This Row],[MONTO7]]) -> 70000000 | S36: =R36-(R36*10%) -> 63000000 | T36: =(S36*1%) -> 630000 | U36: =(Tabla3[[#This Row],[TOTAL -10%]]*Tabla3[[#This Row],[FIDUCIA]]) -> 62370000 | V36: =(Tabla3[[#This Row],[TOTAL -10%]]*Tabla3[[#This Row],[NUBE]]) -> 0 | W36: SI | X36: FIDUCIA | Y36: 0.01 | Z36: 0.99 | AB36: =SUM(Y36:AA36) -> 1 | AC36: =IF(AB36="","",IF(AB36=100%,"OK","ERROR")) -> OK
A37: =(A36+1) -> 17 | B37: 42085517 | C37: CARMEN ADRIANA CASTAÑO CORREA | D37: 17 | E37: =(Tabla3[[#This Row],[CANT]]*5000000) -> 85000000 | F37: 15 | G37: =(Tabla3[[#This Row],[CANT2]]*10000000) -> 150000000 | H37: 3 | I37: =(Tabla3[[#This Row],[CANT3]]*7500000) -> 22500000 | R37: =(Tabla3[[#This Row],[MONTO]]+Tabla3[[#This Row],[MONTO2]]+Tabla3[[#This Row],[MONTO3]]+Tabla3[[#This Row],[MONTO4]]+Tabla3[[#This Row],[MONTO5]]+Tabla3[[#This Row],[MONTO6]]+Tabla3[[#This Row],[MONTO7]]) -> 257500000 | S37: =R37-(R37*10%) -> 231750000 | T37: =(S37*1%) -> 2317500 | U37: =(Tabla3[[#This Row],[TOTAL -10%]]*Tabla3[[#This Row],[FIDUCIA]]) -> 0 | V37: =(Tabla3[[#This Row],[TOTAL -10%]]*Tabla3[[#This Row],[NUBE]]) -> 229432500 | W37: SI | X37: NUBE | Y37: 0.01 | AA37: 0.99 | AB37: =SUM(Y37:AA37) -> 1 | AC37: =IF(AB37="","",IF(AB37=100%,"OK","ERROR")) -> OK
A38: =(A37+1) -> 18 | B38: 4612227 | C38: CELSO NEL ORTEGA CAMPO | D38: 2 | E38: =(Tabla3[[#This Row],[CANT]]*5000000) -> 10000000 | R38: =(Tabla3[[#This Row],[MONTO]]+Tabla3[[#This Row],[MONTO2]]+Tabla3[[#This Row],[MONTO3]]+Tabla3[[#This Row],[MONTO4]]+Tabla3[[#This Row],[MONTO5]]+Tabla3[[#This Row],[MONTO6]]+Tabla3[[#This Row],[MONTO7]]) -> 10000000 | S38: =R38-(R38*10%) -> 9000000 | T38: =(S38*1%) -> 90000 | U38: =(Tabla3[[#This Row],[TOTAL -10%]]*Tabla3[[#This Row],[FIDUCIA]]) -> 0 | V38: =(Tabla3[[#This Row],[TOTAL -10%]]*Tabla3[[#This Row],[NUBE]]) -> 8910000 | W38: SI | X38: NUBE | Y38: 0.01 | AA38: 0.99 | AB38: =SUM(Y38:AA38) -> 1 | AC38: =IF(AB38="","",IF(AB38=100%,"OK","ERROR")) -> OK
A39: =(A38+1) -> 19 | B39: 42081364 | C39: CLAUDIA CRISTINA CASTAÑO CORREA | D39: 24 | E39: =(Tabla3[[#This Row],[CANT]]*5000000) -> 120000000 | F39: 19 | G39: =(Tabla3[[#This Row],[CANT2]]*10000000) -> 190000000 | H39: 6 | I39: =(Tabla3[[#This Row],[CANT3]]*7500000) -> 45000000 | R39: =(Tabla3[[#This Row],[MONTO]]+Tabla3[[#This Row],[MONTO2]]+Tabla3[[#This Row],[MONTO3]]+Tabla3[[#This Row],[MONTO4]]+Tabla3[[#This Row],[MONTO5]]+Tabla3[[#This Row],[MONTO6]]+Tabla3[[#This Row],[MONTO7]]) -> 355000000 | S39: =R39-(R39*10%) -> 319500000 | T39: =(S39*1%) -> 3195000 | U39: =(Tabla3[[#This Row],[TOTAL -10%]]*Tabla3[[#This Row],[FIDUCIA]]) -> 0 | V39: =(Tabla3[[#This Row],[TOTAL -10%]]*Tabla3[[#This Row],[NUBE]]) -> 316305000 | W39: SI | X39: NUBE | Y39: 0.01 | AA39: 0.99 | AB39: =SUM(Y39:AA39) -> 1 | AC39: =IF(AB39="","",IF(AB39=100%,"OK","ERROR")) -> OK
A40: =(A39+1) -> 20 | B40: 34566045 | C40: CLAUDIA ESTELA LOPEZ CAMACHO | D40: 11 | E40: =(Tabla3[[#This Row],[CANT]]*5000000) -> 55000000 | F40: 15 | G40: =(Tabla3[[#This Row],[CANT2]]*10000000) -> 150000000 | H40: 10 | I40: =(Tabla3[[#This Row],[CANT3]]*7500000) -> 75000000 | J40: 3 | K40: =(Tabla3[[#This Row],[CANT4]]*500000) -> 1500000 | R40: =(Tabla3[[#This Row],[MONTO]]+Tabla3[[#This Row],[MONTO2]]+Tabla3[[#This Row],[MONTO3]]+Tabla3[[#This Row],[MONTO4]]+Tabla3[[#This Row],[MONTO5]]+Tabla3[[#This Row],[MONTO6]]+Tabla3[[#This Row],[MONTO7]]) -> 281500000 | S40: =R40-(R40*10%) -> 253350000 | T40: =(S40*1%) -> 2533500 | U40: =(Tabla3[[#This Row],[TOTAL -10%]]*Tabla3[[#This Row],[FIDUCIA]]) -> 0 | V40: =(Tabla3[[#This Row],[TOTAL -10%]]*Tabla3[[#This Row],[NUBE]]) -> 250816500 | W40: SI | X40: NUBE | Y40: 0.01 | AA40: 0.99 | AB40: =SUM(Y40:AA40) -> 1 | AC40: =IF(AB40="","",IF(AB40=100%,"OK","ERROR")) -> OK
A41: =(A40+1) -> 21 | B41: 30337930 | C41: CLAUDIA MARCELA MARULANDA GIRALDO | D41: 2 | E41: =(Tabla3[[#This Row],[CANT]]*5000000) -> 10000000 | F41: 3 | G41: =(Tabla3[[#This Row],[CANT2]]*10000000) -> 30000000 | H41: 2 | I41: =(Tabla3[[#This Row],[CANT3]]*7500000) -> 15000000 | R41: =(Tabla3[[#This Row],[MONTO]]+Tabla3[[#This Row],[MONTO2]]+Tabla3[[#This Row],[MONTO3]]+Tabla3[[#This Row],[MONTO4]]+Tabla3[[#This Row],[MONTO5]]+Tabla3[[#This Row],[MONTO6]]+Tabla3[[#This Row],[MONTO7]]) -> 55000000 | S41: =R41-(R41*10%) -> 49500000 | T41: =(S41*1%) -> 495000 | U41: =(Tabla3[[#This Row],[TOTAL -10%]]*Tabla3[[#This Row],[FIDUCIA]]) -> 49005000 | V41: =(Tabla3[[#This Row],[TOTAL -10%]]*Tabla3[[#This Row],[NUBE]]) -> 0 | W41: SI | X41: FIDUCIA | Y41: 0.01 | Z41: 0.99 | AB41: =SUM(Y41:AA41) -> 1 | AC41: =IF(AB41="","",IF(AB41=100%,"OK","ERROR")) -> OK
A42: =(A41+1) -> 22 | B42: 1053860357 | C42: CRISTIAN DAVID HERRERA MARÍN | D42: 2 | E42: =(Tabla3[[#This Row],[CANT]]*5000000) -> 10000000 | H42: 1 | I42: =(Tabla3[[#This Row],[CANT3]]*7500000) -> 7500000 | R42: =(Tabla3[[#This Row],[MONTO]]+Tabla3[[#This Row],[MONTO2]]+Tabla3[[#This Row],[MONTO3]]+Tabla3[[#This Row],[MONTO4]]+Tabla3[[#This Row],[MONTO5]]+Tabla3[[#This Row],[MONTO6]]+Tabla3[[#This Row],[MONTO7]]) -> 17500000 | S42: =R42-(R42*10%) -> 15750000 | T42: =(S42*1%) -> 157500 | U42: =(Tabla3[[#This Row],[TOTAL -10%]]*Tabla3[[#This Row],[FIDUCIA]]) -> 0 | V42: =(Tabla3[[#This Row],[TOTAL -10%]]*Tabla3[[#This Row],[NUBE]]) -> 15592500 | W42: SI | X42: NUBE | Y42: 0.01 | AA42: 0.99 | AB42: =SUM(Y42:AA42) -> 1 | AC42: =IF(AB42="","",IF(AB42=100%,"OK","ERROR")) -> OK
A43: =(A42+1) -> 23 | B43: 38847495 | C43: CRISTIAN ESTEBAN LEZCANO | D43: 20 | E43: =(Tabla3[[#This Row],[CANT]]*5000000) -> 100000000 | R43: =(Tabla3[[#This Row],[MONTO]]+Tabla3[[#This Row],[MONTO2]]+Tabla3[[#This Row],[MONTO3]]+Tabla3[[#This Row],[MONTO4]]+Tabla3[[#This Row],[MONTO5]]+Tabla3[[#This Row],[MONTO6]]+Tabla3[[#This Row],[MONTO7]]) -> 100000000 | S43: =R43-(R43*10%) -> 90000000 | T43: =(S43*1%) -> 900000 | U43: =(Tabla3[[#This Row],[TOTAL -10%]]*Tabla3[[#This Row],[FIDUCIA]]) -> 0 | V43: =(Tabla3[[#This Row],[TOTAL -10%]]*Tabla3[[#This Row],[NUBE]]) -> 89100000 | W43: SI | X43: NUBE | Y43: 0.01 | AA43: 0.99 | AB43: =SUM(Y43:AA43) -> 1 | AC43: =IF(AB43="","",IF(AB43=100%,"OK","ERROR")) -> OK
A44: =(A43+1) -> 24 | B44: 40369286 | C44: DELIA MARIA REY ACOSTA | D44: 5 | E44: =(Tabla3[[#This Row],[CANT]]*5000000) -> 25000000 | R44: =(Tabla3[[#This Row],[MONTO]]+Tabla3[[#This Row],[MONTO2]]+Tabla3[[#This Row],[MONTO3]]+Tabla3[[#This Row],[MONTO4]]+Tabla3[[#This Row],[MONTO5]]+Tabla3[[#This Row],[MONTO6]]+Tabla3[[#This Row],[MONTO7]]) -> 25000000 | S44: =R44-(R44*10%) -> 22500000 | T44: =(S44*1%) -> 225000 | U44: =(Tabla3[[#This Row],[TOTAL -10%]]*Tabla3[[#This Row],[FIDUCIA]]) -> 22275000 | V44: =(Tabla3[[#This Row],[TOTAL -10%]]*Tabla3[[#This Row],[NUBE]]) -> 0 | W44: SI | X44: FIDUCIA | Y44: 0.01 | Z44: 0.99 | AB44: =SUM(Y44:AA44) -> 1 | AC44: =IF(AB44="","",IF(AB44=100%,"OK","ERROR")) -> OK
A45: =(A44+1) -> 25 | B45: 43872922 | C45: DIANA MARCELA SANCHEZ MARIN | D45: 4 | E45: =(Tabla3[[#This Row],[CANT]]*5000000) -> 20000000 | F45: 4 | G45: =(Tabla3[[#This Row],[CANT2]]*10000000) -> 40000000 | L45: 1 | M45: =(L45*12500000) -> 12500000 | N45: 1 | O45: =(N45*200000) -> 200000 | R45: =(Tabla3[[#This Row],[MONTO]]+Tabla3[[#This Row],[MONTO2]]+Tabla3[[#This Row],[MONTO3]]+Tabla3[[#This Row],[MONTO4]]+Tabla3[[#This Row],[MONTO5]]+Tabla3[[#This Row],[MONTO6]]+Tabla3[[#This Row],[MONTO7]]) -> 72700000 | S45: =R45-(R45*10%) -> 65430000 | T45: =(S45*1%) -> 654300 | U45: =(Tabla3[[#This Row],[TOTAL -10%]]*Tabla3[[#This Row],[FIDUCIA]]) -> 0 | V45: =(Tabla3[[#This Row],[TOTAL -10%]]*Tabla3[[#This Row],[NUBE]]) -> 64775700 | W45: SI | X45: NUBE | Y45: 0.01 | AA45: 0.99 | AB45: =SUM(Y45:AA45) -> 1 | AC45: =IF(AB45="","",IF(AB45=100%,"OK","ERROR")) -> OK
A46: =(A45+1) -> 26 | B46: 29832605 | C46: DIANA PATRICIA ARBELAEZ FLOREZ | D46: 20 | E46: =(Tabla3[[#This Row],[CANT]]*5000000) -> 100000000 | F46: 12 | G46: =(Tabla3[[#This Row],[CANT2]]*10000000) -> 120000000 | H46: 12 | I46: =(Tabla3[[#This Row],[CANT3]]*7500000) -> 90000000 | L46: 1 | M46: =(L46*12500000) -> 12500000 | R46: =(Tabla3[[#This Row],[MONTO]]+Tabla3[[#This Row],[MONTO2]]+Tabla3[[#This Row],[MONTO3]]+Tabla3[[#This Row],[MONTO4]]+Tabla3[[#This Row],[MONTO5]]+Tabla3[[#This Row],[MONTO6]]+Tabla3[[#This Row],[MONTO7]]) -> 322500000 | S46: =R46-(R46*10%) -> 290250000 | T46: =(S46*1%) -> 2902500 | U46: =(Tabla3[[#This Row],[TOTAL -10%]]*Tabla3[[#This Row],[FIDUCIA]]) -> 0 | V46: =(Tabla3[[#This Row],[TOTAL -10%]]*Tabla3[[#This Row],[NUBE]]) -> 287347500 | W46: SI | X46: NUBE | Y46: 0.01 | AA46: 0.99 | AB46: =SUM(Y46:AA46) -> 1 | AC46: =IF(AB46="","",IF(AB46=100%,"OK","ERROR")) -> OK
A47: =(A46+1) -> 27 | B47: 10298946 | C47: DIEGO FELIPE MAZORRA | D47: 1 | E47: =(Tabla3[[#This Row],[CANT]]*5000000) -> 5000000 | J47: 1 | K47: =(Tabla3[[#This Row],[CANT4]]*500000) -> 500000 | R47: =(Tabla3[[#This Row],[MONTO]]+Tabla3[[#This Row],[MONTO2]]+Tabla3[[#This Row],[MONTO3]]+Tabla3[[#This Row],[MONTO4]]+Tabla3[[#This Row],[MONTO5]]+Tabla3[[#This Row],[MONTO6]]+Tabla3[[#This Row],[MONTO7]]) -> 5500000 | S47: =R47-(R47*10%) -> 4950000 | T47: =(S47*1%) -> 49500 | U47: =(Tabla3[[#This Row],[TOTAL -10%]]*Tabla3[[#This Row],[FIDUCIA]]) -> 4900500 | V47: =(Tabla3[[#This Row],[TOTAL -10%]]*Tabla3[[#This Row],[NUBE]]) -> 0 | W47: SI | X47: FIDUCIA | Y47: 0.01 | Z47: 0.99 | AB47: =SUM(Y47:AA47) -> 1 | AC47: =IF(AB47="","",IF(AB47=100%,"OK","ERROR")) -> OK
A48: =(A47+1) -> 28 | B48: 13700726 | C48: ELIAS SANABRIA MELGAREJO | D48: 37 | E48: =(Tabla3[[#This Row],[CANT]]*5000000) -> 185000000 | F48: 2 | G48: =(Tabla3[[#This Row],[CANT2]]*10000000) -> 20000000 | H48: 1 | I48: =(Tabla3[[#This Row],[CANT3]]*7500000) -> 7500000 | R48: =(Tabla3[[#This Row],[MONTO]]+Tabla3[[#This Row],[MONTO2]]+Tabla3[[#This Row],[MONTO3]]+Tabla3[[#This Row],[MONTO4]]+Tabla3[[#This Row],[MONTO5]]+Tabla3[[#This Row],[MONTO6]]+Tabla3[[#This Row],[MONTO7]]) -> 212500000 | S48: =R48-(R48*10%) -> 191250000 | T48: =(S48*1%) -> 1912500 | U48: =(Tabla3[[#This Row],[TOTAL -10%]]*Tabla3[[#This Row],[FIDUCIA]]) -> 0 | V48: =(Tabla3[[#This Row],[TOTAL -10%]]*Tabla3[[#This Row],[NUBE]]) -> 189337500 | W48: SI | X48: NUBE | Y48: 0.01 | AA48: 0.99 | AB48: =SUM(Y48:AA48) -> 1 | AC48: =IF(AB48="","",IF(AB48=100%,"OK","ERROR")) -> OK
A49: =(A48+1) -> 29 | B49: 30332751 | C49: ELSA PATRICIA MARULANDA GIRALDO | D49: 4 | E49: =(Tabla3[[#This Row],[CANT]]*5000000) -> 20000000 | F49: 3 | G49: =(Tabla3[[#This Row],[CANT2]]*10000000) -> 30000000 | R49: =(Tabla3[[#This Row],[MONTO]]+Tabla3[[#This Row],[MONTO2]]+Tabla3[[#This Row],[MONTO3]]+Tabla3[[#This Row],[MONTO4]]+Tabla3[[#This Row],[MONTO5]]+Tabla3[[#This Row],[MONTO6]]+Tabla3[[#This Row],[MONTO7]]) -> 50000000 | S49: =R49-(R49*10%) -> 45000000 | T49: =(S49*1%) -> 450000 | U49: =(Tabla3[[#This Row],[TOTAL -10%]]*Tabla3[[#This Row],[FIDUCIA]]) -> 44550000 | V49: =(Tabla3[[#This Row],[TOTAL -10%]]*Tabla3[[#This Row],[NUBE]]) -> 0 | W49: SI | X49: FIDUCIA | Y49: 0.01 | Z49: 0.99 | AB49: =SUM(Y49:AA49) -> 1 | AC49: =IF(AB49="","",IF(AB49=100%,"OK","ERROR")) -> OK
A50: =(A49+1) -> 30 | B50: 34553021 | C50: EMILSEN YANGANA OLIVAR | D50: 16 | E50: =(Tabla3[[#This Row],[CANT]]*5000000) -> 80000000 | R50: =(Tabla3[[#This Row],[MONTO]]+Tabla3[[#This Row],[MONTO2]]+Tabla3[[#This Row],[MONTO3]]+Tabla3[[#This Row],[MONTO4]]+Tabla3[[#This Row],[MONTO5]]+Tabla3[[#This Row],[MONTO6]]+Tabla3[[#This Row],[MONTO7]]) -> 80000000 | S50: =R50-(R50*10%) -> 72000000 | T50: =(S50*1%) -> 720000 | U50: =(Tabla3[[#This Row],[TOTAL -10%]]*Tabla3[[#This Row],[FIDUCIA]]) -> 71280000 | V50: =(Tabla3[[#This Row],[TOTAL -10%]]*Tabla3[[#This Row],[NUBE]]) -> 0 | W50: SI | X50: FIDUCIA | Y50: 0.01 | Z50: 0.99 | AB50: =SUM(Y50:AA50) -> 1 | AC50: =IF(AB50="","",IF(AB50=100%,"OK","ERROR")) -> OK
A51: =(A50+1) -> 31 | B51: 43793721 | C51: ERICKA YAMILE VALENCIA GOMEZ | D51: 108 | E51: =(Tabla3[[#This Row],[CANT]]*5000000) -> 540000000 | F51: 5 | G51: =(Tabla3[[#This Row],[CANT2]]*10000000) -> 50000000 | H51: 2 | I51: =(Tabla3[[#This Row],[CANT3]]*7500000) -> 15000000 | J51: 3 | K51: =(Tabla3[[#This Row],[CANT4]]*500000) -> 1500000 | R51: =(Tabla3[[#This Row],[MONTO]]+Tabla3[[#This Row],[MONTO2]]+Tabla3[[#This Row],[MONTO3]]+Tabla3[[#This Row],[MONTO4]]+Tabla3[[#This Row],[MONTO5]]+Tabla3[[#This Row],[MONTO6]]+Tabla3[[#This Row],[MONTO7]]) -> 606500000 | S51: =R51-(R51*10%) -> 545850000 | T51: =(S51*1%) -> 5458500 | U51: =(Tabla3[[#This Row],[TOTAL -10%]]*Tabla3[[#This Row],[FIDUCIA]]) -> 540391500 | V51: =(Tabla3[[#This Row],[TOTAL -10%]]*Tabla3[[#This Row],[NUBE]]) -> 0 | W51: SI | X51: FIDUCIA | Y51: 0.01 | Z51: 0.99 | AB51: =SUM(Y51:AA51) -> 1 | AC51: =IF(AB51="","",IF(AB51=100%,"OK","ERROR")) -> OK
A52: =(A51+1) -> 32 | B52: 1053848679 | C52: ERIK ALEJANDRO CASTAÑEDA CANO | D52: 2 | E52: =(Tabla3[[#This Row],[CANT]]*5000000) -> 10000000 | F52: 5 | G52: =(Tabla3[[#This Row],[CANT2]]*10000000) -> 50000000 | H52: 1 | I52: =(Tabla3[[#This Row],[CANT3]]*7500000) -> 7500000 | R52: =(Tabla3[[#This Row],[MONTO]]+Tabla3[[#This Row],[MONTO2]]+Tabla3[[#This Row],[MONTO3]]+Tabla3[[#This Row],[MONTO4]]+Tabla3[[#This Row],[MONTO5]]+Tabla3[[#This Row],[MONTO6]]+Tabla3[[#This Row],[MONTO7]]) -> 67500000 | S52: =R52-(R52*10%) -> 60750000 | T52: =(S52*1%) -> 607500 | U52: =(Tabla3[[#This Row],[TOTAL -10%]]*Tabla3[[#This Row],[FIDUCIA]]) -> 0 | V52: =(Tabla3[[#This Row],[TOTAL -10%]]*Tabla3[[#This Row],[NUBE]]) -> 60142500 | W52: SI | X52: NUBE | Y52: 0.01 | AA52: 0.99 | AB52: =SUM(Y52:AA52) -> 1 | AC52: =IF(AB52="","",IF(AB52=100%,"OK","ERROR")) -> OK
A53: =(A52+1) -> 33 | B53: 1063812968 | C53: FRANCY YULIANA BOLAÑOS PERAFAN | D53: 4 | E53: =(Tabla3[[#This Row],[CANT]]*5000000) -> 20000000 | F53: 6 | G53: =(Tabla3[[#This Row],[CANT2]]*10000000) -> 60000000 | H53: 4 | I53: =(Tabla3[[#This Row],[CANT3]]*7500000) -> 30000000 | R53: =(Tabla3[[#This Row],[MONTO]]+Tabla3[[#This Row],[MONTO2]]+Tabla3[[#This Row],[MONTO3]]+Tabla3[[#This Row],[MONTO4]]+Tabla3[[#This Row],[MONTO5]]+Tabla3[[#This Row],[MONTO6]]+Tabla3[[#This Row],[MONTO7]]) -> 110000000 | S53: =R53-(R53*10%) -> 99000000 | T53: =(S53*1%) -> 990000 | U53: =(Tabla3[[#This Row],[TOTAL -10%]]*Tabla3[[#This Row],[FIDUCIA]]) -> 98010000 | V53: =(Tabla3[[#This Row],[TOTAL -10%]]*Tabla3[[#This Row],[NUBE]]) -> 0 | W53: SI | X53: FIDUCIA | Y53: 0.01 | Z53: 0.99 | AB53: =SUM(Y53:AA53) -> 1 | AC53: =IF(AB53="","",IF(AB53=100%,"OK","ERROR")) -> OK
A54: =(A53+1) -> 34 | B54: 31423160 | C54: FRANS ORFINDEY GUTIERREZ NOREÑA | D54: 5 | E54: =(Tabla3[[#This Row],[CANT]]*5000000) -> 25000000 | R54: =(Tabla3[[#This Row],[MONTO]]+Tabla3[[#This Row],[MONTO2]]+Tabla3[[#This Row],[MONTO3]]+Tabla3[[#This Row],[MONTO4]]+Tabla3[[#This Row],[MONTO5]]+Tabla3[[#This Row],[MONTO6]]+Tabla3[[#This Row],[MONTO7]]) -> 25000000 | S54: =R54-(R54*10%) -> 22500000 | T54: =(S54*1%) -> 225000 | U54: =(Tabla3[[#This Row],[TOTAL -10%]]*Tabla3[[#This Row],[FIDUCIA]]) -> 0 | V54: =(Tabla3[[#This Row],[TOTAL -10%]]*Tabla3[[#This Row],[NUBE]]) -> 22275000 | W54: SI | X54: NUBE | Y54: 0.01 | AA54: 0.99 | AB54: =SUM(Y54:AA54) -> 1 | AC54: =IF(AB54="","",IF(AB54=100%,"OK","ERROR")) -> OK
A55: =(A54+1) -> 35 | B55: 801588047 | C55: FREDA YANARA TELLO LÓPEZ | D55: 2 | E55: =(Tabla3[[#This Row],[CANT]]*5000000) -> 10000000 | F55: 2 | G55: =(Tabla3[[#This Row],[CANT2]]*10000000) -> 20000000 | R55: =(Tabla3[[#This Row],[MONTO]]+Tabla3[[#This Row],[MONTO2]]+Tabla3[[#This Row],[MONTO3]]+Tabla3[[#This Row],[MONTO4]]+Tabla3[[#This Row],[MONTO5]]+Tabla3[[#This Row],[MONTO6]]+Tabla3[[#This Row],[MONTO7]]) -> 30000000 | S55: =R55-(R55*10%) -> 27000000 | T55: =(S55*1%) -> 270000 | U55: =(Tabla3[[#This Row],[TOTAL -10%]]*Tabla3[[#This Row],[FIDUCIA]]) -> 0 | V55: =(Tabla3[[#This Row],[TOTAL -10%]]*Tabla3[[#This Row],[NUBE]]) -> 26730000 | W55: SI | X55: NUBE | Y55: 0.01 | AA55: 0.99 | AB55: =SUM(Y55:AA55) -> 1 | AC55: =IF(AB55="","",IF(AB55=100%,"OK","ERROR")) -> OK
A56: =(A55+1) -> 36 | B56: 0802595819 | C56: FREDDY RUBEN CAICEDO GRACIA | D56: 5 | E56: =(Tabla3[[#This Row],[CANT]]*5000000) -> 25000000 | F56: 1 | G56: =(Tabla3[[#This Row],[CANT2]]*10000000) -> 10000000 | R56: =(Tabla3[[#This Row],[MONTO]]+Tabla3[[#This Row],[MONTO2]]+Tabla3[[#This Row],[MONTO3]]+Tabla3[[#This Row],[MONTO4]]+Tabla3[[#This Row],[MONTO5]]+Tabla3[[#This Row],[MONTO6]]+Tabla3[[#This Row],[MONTO7]]) -> 35000000 | S56: =R56-(R56*10%) -> 31500000 | T56: =(S56*1%) -> 315000 | U56: =(Tabla3[[#This Row],[TOTAL -10%]]*Tabla3[[#This Row],[FIDUCIA]]) -> 0 | V56: =(Tabla3[[#This Row],[TOTAL -10%]]*Tabla3[[#This Row],[NUBE]]) -> 31185000 | W56: SI | X56: NUBE | Y56: 0.01 | AA56: 0.99 | AB56: =SUM(Y56:AA56) -> 1 | AC56: =IF(AB56="","",IF(AB56=100%,"OK","ERROR")) -> OK
A57: =(A56+1) -> 37 | B57: 94287342 | C57: GEOVANY BUITRAGO RAMIREZ | D57: 7 | E57: =(Tabla3[[#This Row],[CANT]]*5000000) -> 35000000 | F57: 2 | G57: =(Tabla3[[#This Row],[CANT2]]*10000000) -> 20000000 | R57: =(Tabla3[[#This Row],[MONTO]]+Tabla3[[#This Row],[MONTO2]]+Tabla3[[#This Row],[MONTO3]]+Tabla3[[#This Row],[MONTO4]]+Tabla3[[#This Row],[MONTO5]]+Tabla3[[#This Row],[MONTO6]]+Tabla3[[#This Row],[MONTO7]]) -> 55000000 | S57: =R57-(R57*10%) -> 49500000 | T57: =(S57*1%) -> 495000 | U57: =(Tabla3[[#This Row],[TOTAL -10%]]*Tabla3[[#This Row],[FIDUCIA]]) -> 49005000 | V57: =(Tabla3[[#This Row],[TOTAL -10%]]*Tabla3[[#This Row],[NUBE]]) -> 0 | W57: SI | X57: FIDUCIA | Y57: 0.01 | Z57: 0.99 | AB57: =SUM(Y57:AA57) -> 1 | AC57: =IF(AB57="","",IF(AB57=100%,"OK","ERROR")) -> OK
A58: =(A57+1) -> 38 | B58: 25154026 | C58: GIRINEIRIE CARDONA RESTREPO | D58: 18 | E58: =(Tabla3[[#This Row],[CANT]]*5000000) -> 90000000 | J58: 1 | K58: =(Tabla3[[#This Row],[CANT4]]*500000) -> 500000 | R58: =(Tabla3[[#This Row],[MONTO]]+Tabla3[[#This Row],[MONTO2]]+Tabla3[[#This Row],[MONTO3]]+Tabla3[[#This Row],[MONTO4]]+Tabla3[[#This Row],[MONTO5]]+Tabla3[[#This Row],[MONTO6]]+Tabla3[[#This Row],[MONTO7]]) -> 90500000 | S58: =R58-(R58*10%) -> 81450000 | T58: =(S58*1%) -> 814500 | U58: =(Tabla3[[#This Row],[TOTAL -10%]]*Tabla3[[#This Row],[FIDUCIA]]) -> 80635500 | V58: =(Tabla3[[#This Row],[TOTAL -10%]]*Tabla3[[#This Row],[NUBE]]) -> 0 | W58: SI | X58: FIDUCIA | Y58: 0.01 | Z58: 0.99 | AB58: =SUM(Y58:AA58) -> 1 | AC58: =IF(AB58="","",IF(AB58=100%,"OK","ERROR")) -> OK
A59: =(A58+1) -> 39 | B59: 10268009 | C59: GUSTAVO CASTAÑO LONDOÑO | D59: 2 | E59: =(Tabla3[[#This Row],[CANT]]*5000000) -> 10000000 | F59: 2 | G59: =(Tabla3[[#This Row],[CANT2]]*10000000) -> 20000000 | R59: =(Tabla3[[#This Row],[MONTO]]+Tabla3[[#This Row],[MONTO2]]+Tabla3[[#This Row],[MONTO3]]+Tabla3[[#This Row],[MONTO4]]+Tabla3[[#This Row],[MONTO5]]+Tabla3[[#This Row],[MONTO6]]+Tabla3[[#This Row],[MONTO7]]) -> 30000000 | S59: =R59-(R59*10%) -> 27000000 | T59: =(S59*1%) -> 270000 | U59: =(Tabla3[[#This Row],[TOTAL -10%]]*Tabla3[[#This Row],[FIDUCIA]]) -> 26730000 | V59: =(Tabla3[[#This Row],[TOTAL -10%]]*Tabla3[[#This Row],[NUBE]]) -> 0 | W59: SI | X59: FIDUCIA | Y59: 0.01 | Z59: 0.99 | AB59: =SUM(Y59:AA59) -> 1 | AC59: =IF(AB59="","",IF(AB59=100%,"OK","ERROR")) -> OK
A60: =(A59+1) -> 40 | B60: 98663385 | C60: HERNAN ALONSO MONTOYA BARRIENTOS | D60: 21 | E60: =(Tabla3[[#This Row],[CANT]]*5000000) -> 105000000 | R60: =(Tabla3[[#This Row],[MONTO]]+Tabla3[[#This Row],[MONTO2]]+Tabla3[[#This Row],[MONTO3]]+Tabla3[[#This Row],[MONTO4]]+Tabla3[[#This Row],[MONTO5]]+Tabla3[[#This Row],[MONTO6]]+Tabla3[[#This Row],[MONTO7]]) -> 105000000 | S60: =R60-(R60*10%) -> 94500000 | T60: =(S60*1%) -> 945000 | U60: =(Tabla3[[#This Row],[TOTAL -10%]]*Tabla3[[#This Row],[FIDUCIA]]) -> 93555000 | V60: =(Tabla3[[#This Row],[TOTAL -10%]]*Tabla3[[#This Row],[NUBE]]) -> 0 | W60: SI | X60: FIDUCIA | Y60: 0.01 | Z60: 0.99 | AB60: =SUM(Y60:AA60) -> 1 | AC60: =IF(AB60="","",IF(AB60=100%,"OK","ERROR")) -> OK
A61: =(A60+1) -> 41 | B61: 802346288 | C61: IVIS LEONORA LAJONES RUANO | D61: 2 | E61: =(Tabla3[[#This Row],[CANT]]*5000000) -> 10000000 | F61: 3 | G61: =(Tabla3[[#This Row],[CANT2]]*10000000) -> 30000000 | H61: 2 | I61: =(Tabla3[[#This Row],[CANT3]]*7500000) -> 15000000 | R61: =(Tabla3[[#This Row],[MONTO]]+Tabla3[[#This Row],[MONTO2]]+Tabla3[[#This Row],[MONTO3]]+Tabla3[[#This Row],[MONTO4]]+Tabla3[[#This Row],[MONTO5]]+Tabla3[[#This Row],[MONTO6]]+Tabla3[[#This Row],[MONTO7]]) -> 55000000 | S61: =R61-(R61*10%) -> 49500000 | T61: =(S61*1%) -> 495000 | U61: =(Tabla3[[#This Row],[TOTAL -10%]]*Tabla3[[#This Row],[FIDUCIA]]) -> 0 | V61: =(Tabla3[[#This Row],[TOTAL -10%]]*Tabla3[[#This Row],[NUBE]]) -> 49005000 | W61: SI | X61: NUBE | Y61: 0.01 | AA61: 0.99 | AB61: =SUM(Y61:AA61) -> 1 | AC61: =IF(AB61="","",IF(AB61=100%,"OK","ERROR")) -> OK
A62: =(A61+1) -> 42 | B62: 1047367059 | C62: IVON NATALIA MONTOYA DUQUE | D62: 11 | E62: =(Tabla3[[#This Row],[CANT]]*5000000) -> 55000000 | F62: 8 | G62: =(Tabla3[[#This Row],[CANT2]]*10000000) -> 80000000 | R62: =(Tabla3[[#This Row],[MONTO]]+Tabla3[[#This Row],[MONTO2]]+Tabla3[[#This Row],[MONTO3]]+Tabla3[[#This Row],[MONTO4]]+Tabla3[[#This Row],[MONTO5]]+Tabla3[[#This Row],[MONTO6]]+Tabla3[[#This Row],[MONTO7]]) -> 135000000 | S62: =R62-(R62*10%) -> 121500000 | T62: =(S62*1%) -> 1215000 | U62: =(Tabla3[[#This Row],[TOTAL -10%]]*Tabla3[[#This Row],[FIDUCIA]]) -> 0 | V62: =(Tabla3[[#This Row],[TOTAL -10%]]*Tabla3[[#This Row],[NUBE]]) -> 120285000 | W62: SI | X62: NUBE | Y62: 0.01 | AA62: 0.99 | AB62: =SUM(Y62:AA62) -> 1 | AC62: =IF(AB62="","",IF(AB62=100%,"OK","ERROR")) -> OK
A63: =(A62+1) -> 43 | B63: 10009797 | C63: JADER MAURICIO VANEGAS SANCHEZ | D63: 22 | E63: =(Tabla3[[#This Row],[CANT]]*5000000) -> 110000000 | F63: 1 | G63: =(Tabla3[[#This Row],[CANT2]]*10000000) -> 10000000 | H63: 1 | I63: =(Tabla3[[#This Row],[CANT3]]*7500000) -> 7500000 | R63: =(Tabla3[[#This Row],[MONTO]]+Tabla3[[#This Row],[MONTO2]]+Tabla3[[#This Row],[MONTO3]]+Tabla3[[#This Row],[MONTO4]]+Tabla3[[#This Row],[MONTO5]]+Tabla3[[#This Row],[MONTO6]]+Tabla3[[#This Row],[MONTO7]]) -> 127500000 | S63: =R63-(R63*10%) -> 114750000 | T63: =(S63*1%) -> 1147500 | U63: =(Tabla3[[#This Row],[TOTAL -10%]]*Tabla3[[#This Row],[FIDUCIA]]) -> 113602500 | V63: =(Tabla3[[#This Row],[TOTAL -10%]]*Tabla3[[#This Row],[NUBE]]) -> 0 | W63: SI | X63: FIDUCIA | Y63: 0.01 | Z63: 0.99 | AB63: =SUM(Y63:AA63) -> 1 | AC63: =IF(AB63="","",IF(AB63=100%,"OK","ERROR")) -> OK
A64: =(A63+1) -> 44 | B64: 802949131 | C64: JAVIER DAVID VACA MERO | D64: 4 | E64: =(Tabla3[[#This Row],[CANT]]*5000000) -> 20000000 | F64: 4 | G64: =(Tabla3[[#This Row],[CANT2]]*10000000) -> 40000000 | H64: 2 | I64: =(Tabla3[[#This Row],[CANT3]]*7500000) -> 15000000 | R64: =(Tabla3[[#This Row],[MONTO]]+Tabla3[[#This Row],[MONTO2]]+Tabla3[[#This Row],[MONTO3]]+Tabla3[[#This Row],[MONTO4]]+Tabla3[[#This Row],[MONTO5]]+Tabla3[[#This Row],[MONTO6]]+Tabla3[[#This Row],[MONTO7]]) -> 75000000 | S64: =R64-(R64*10%) -> 67500000 | T64: =(S64*1%) -> 675000 | U64: =(Tabla3[[#This Row],[TOTAL -10%]]*Tabla3[[#This Row],[FIDUCIA]]) -> 0 | V64: =(Tabla3[[#This Row],[TOTAL -10%]]*Tabla3[[#This Row],[NUBE]]) -> 66825000 | W64: SI | X64: NUBE | Y64: 0.01 | AA64: 0.99 | AB64: =SUM(Y64:AA64) -> 1 | AC64: =IF(AB64="","",IF(AB64=100%,"OK","ERROR")) -> OK
A65: =(A64+1) -> 45 | B65: 1012360238 | C65: JAYER MARTINEZ CASTRO | H65: 1 | I65: =(Tabla3[[#This Row],[CANT3]]*7500000) -> 7500000 | R65: =(Tabla3[[#This Row],[MONTO]]+Tabla3[[#This Row],[MONTO2]]+Tabla3[[#This Row],[MONTO3]]+Tabla3[[#This Row],[MONTO4]]+Tabla3[[#This Row],[MONTO5]]+Tabla3[[#This Row],[MONTO6]]+Tabla3[[#This Row],[MONTO7]]) -> 7500000 | S65: =R65-(R65*10%) -> 6750000 | T65: =(S65*1%) -> 67500 | U65: =(Tabla3[[#This Row],[TOTAL -10%]]*Tabla3[[#This Row],[FIDUCIA]]) -> 6682500 | V65: =(Tabla3[[#This Row],[TOTAL -10%]]*Tabla3[[#This Row],[NUBE]]) -> 0 | W65: SI | X65: FIDUCIA | Y65: 0.01 | Z65: 0.99 | AB65: =SUM(Y65:AA65) -> 1 | AC65: =IF(AB65="","",IF(AB65=100%,"OK","ERROR")) -> OK
A66: =(A65+1) -> 46 | B66: 1061822047 | C66: JEISON ALEXIS LOPEZ CORDOBA | D66: 1 | E66: =(Tabla3[[#This Row],[CANT]]*5000000) -> 5000000 | R66: =(Tabla3[[#This Row],[MONTO]]+Tabla3[[#This Row],[MONTO2]]+Tabla3[[#This Row],[MONTO3]]+Tabla3[[#This Row],[MONTO4]]+Tabla3[[#This Row],[MONTO5]]+Tabla3[[#This Row],[MONTO6]]+Tabla3[[#This Row],[MONTO7]]) -> 5000000 | S66: =R66-(R66*10%) -> 4500000 | T66: =(S66*1%) -> 45000 | U66: =(Tabla3[[#This Row],[TOTAL -10%]]*Tabla3[[#This Row],[FIDUCIA]]) -> 0 | V66: =(Tabla3[[#This Row],[TOTAL -10%]]*Tabla3[[#This Row],[NUBE]]) -> 4455000 | W66: SI | X66: NUBE | Y66: 0.01 | AA66: 0.99 | AB66: =SUM(Y66:AA66) -> 1 | AC66: =IF(AB66="","",IF(AB66=100%,"OK","ERROR")) -> OK
A67: =(A66+1) -> 47 | B67: 1045417404 | C67: JHEN JADY CARVALLO PARRA | D67: 5 | E67: =(Tabla3[[#This Row],[CANT]]*5000000) -> 25000000 | R67: =(Tabla3[[#This Row],[MONTO]]+Tabla3[[#This Row],[MONTO2]]+Tabla3[[#This Row],[MONTO3]]+Tabla3[[#This Row],[MONTO4]]+Tabla3[[#This Row],[MONTO5]]+Tabla3[[#This Row],[MONTO6]]+Tabla3[[#This Row],[MONTO7]]) -> 25000000 | S67: =R67-(R67*10%) -> 22500000 | T67: =(S67*1%) -> 225000 | U67: =(Tabla3[[#This Row],[TOTAL -10%]]*Tabla3[[#This Row],[FIDUCIA]]) -> 0 | V67: =(Tabla3[[#This Row],[TOTAL -10%]]*Tabla3[[#This Row],[NUBE]]) -> 22275000 | W67: SI | X67: NUBE | Y67: 0.01 | AA67: 0.99 | AB67: =SUM(Y67:AA67) -> 1 | AC67: =IF(AB67="","",IF(AB67=100%,"OK","ERROR")) -> OK
A68: =(A67+1) -> 48 | B68: 18510129 | C68: JHON JADER OYOLA OSORIO | D68: 146 | E68: =(Tabla3[[#This Row],[CANT]]*5000000) -> 730000000 | F68: 60 | G68: =(Tabla3[[#This Row],[CANT2]]*10000000) -> 600000000 | H68: 16 | I68: =(Tabla3[[#This Row],[CANT3]]*7500000) -> 120000000 | J68: 6 | K68: =(Tabla3[[#This Row],[CANT4]]*500000) -> 3000000 | R68: =(Tabla3[[#This Row],[MONTO]]+Tabla3[[#This Row],[MONTO2]]+Tabla3[[#This Row],[MONTO3]]+Tabla3[[#This Row],[MONTO4]]+Tabla3[[#This Row],[MONTO5]]+Tabla3[[#This Row],[MONTO6]]+Tabla3[[#This Row],[MONTO7]]) -> 1453000000 | S68: =R68-(R68*10%) -> 1307700000 | T68: =(S68*1%) -> 13077000 | U68: =(Tabla3[[#This Row],[TOTAL -10%]]*Tabla3[[#This Row],[FIDUCIA]]) -> 0 | V68: =(Tabla3[[#This Row],[TOTAL -10%]]*Tabla3[[#This Row],[NUBE]]) -> 1294623000 | W68: SI | X68: NUBE | Y68: 0.01 | AA68: 0.99 | AB68: =SUM(Y68:AA68) -> 1 | AC68: =IF(AB68="","",IF(AB68=100%,"OK","ERROR")) -> OK
A69: =(A68+1) -> 49 | B69: 12916817 | C69: JHON LUIS CRUEL MARIN | D69: 5 | E69: =(Tabla3[[#This Row],[CANT]]*5000000) -> 25000000 | R69: =(Tabla3[[#This Row],[MONTO]]+Tabla3[[#This Row],[MONTO2]]+Tabla3[[#This Row],[MONTO3]]+Tabla3[[#This Row],[MONTO4]]+Tabla3[[#This Row],[MONTO5]]+Tabla3[[#This Row],[MONTO6]]+Tabla3[[#This Row],[MONTO7]]) -> 25000000 | S69: =R69-(R69*10%) -> 22500000 | T69: =(S69*1%) -> 225000 | U69: =(Tabla3[[#This Row],[TOTAL -10%]]*Tabla3[[#This Row],[FIDUCIA]]) -> 0 | V69: =(Tabla3[[#This Row],[TOTAL -10%]]*Tabla3[[#This Row],[NUBE]]) -> 22275000 | W69: SI | X69: NUBE | Y69: 0.01 | AA69: 0.99 | AB69: =SUM(Y69:AA69) -> 1 | AC69: =IF(AB69="","",IF(AB69=100%,"OK","ERROR")) -> OK
A70: =(A69+1) -> 50 | B70: 801051038 | C70: JIMMY ADOLFO CASTILLO QUINTERO | D70: 1 | E70: =(Tabla3[[#This Row],[CANT]]*5000000) -> 5000000 | F70: 1 | G70: =(Tabla3[[#This Row],[CANT2]]*10000000) -> 10000000 | H70: 2 | I70: =(Tabla3[[#This Row],[CANT3]]*7500000) -> 15000000 | R70: =(Tabla3[[#This Row],[MONTO]]+Tabla3[[#This Row],[MONTO2]]+Tabla3[[#This Row],[MONTO3]]+Tabla3[[#This Row],[MONTO4]]+Tabla3[[#This Row],[MONTO5]]+Tabla3[[#This Row],[MONTO6]]+Tabla3[[#This Row],[MONTO7]]) -> 30000000 | S70: =R70-(R70*10%) -> 27000000 | T70: =(S70*1%) -> 270000 | U70: =(Tabla3[[#This Row],[TOTAL -10%]]*Tabla3[[#This Row],[FIDUCIA]]) -> 0 | V70: =(Tabla3[[#This Row],[TOTAL -10%]]*Tabla3[[#This Row],[NUBE]]) -> 26730000 | W70: SI | X70: NUBE | Y70: 0.01 | AA70: 0.99 | AB70: =SUM(Y70:AA70) -> 1 | AC70: =IF(AB70="","",IF(AB70=100%,"OK","ERROR")) -> OK
A71: =(A70+1) -> 51 | B71: 85477130 | C71: JOHAN HAROLD FRAGOSO CARRILLO | D71: 5 | E71: =(Tabla3[[#This Row],[CANT]]*5000000) -> 25000000 | F71: 2 | G71: =(Tabla3[[#This Row],[CANT2]]*10000000) -> 20000000 | R71: =(Tabla3[[#This Row],[MONTO]]+Tabla3[[#This Row],[MONTO2]]+Tabla3[[#This Row],[MONTO3]]+Tabla3[[#This Row],[MONTO4]]+Tabla3[[#This Row],[MONTO5]]+Tabla3[[#This Row],[MONTO6]]+Tabla3[[#This Row],[MONTO7]]) -> 45000000 | S71: =R71-(R71*10%) -> 40500000 | T71: =(S71*1%) -> 405000 | U71: =(Tabla3[[#This Row],[TOTAL -10%]]*Tabla3[[#This Row],[FIDUCIA]]) -> 0 | V71: =(Tabla3[[#This Row],[TOTAL -10%]]*Tabla3[[#This Row],[NUBE]]) -> 40095000 | W71: SI | X71: NUBE | Y71: 0.01 | AA71: 0.99 | AB71: =SUM(Y71:AA71) -> 1 | AC71: =IF(AB71="","",IF(AB71=100%,"OK","ERROR")) -> OK
A72: =(A71+1) -> 52 | B72: 1053808723 | C72: JOHANA TATIANA CASTAÑEDA CANO | D72: 140 | E72: =(Tabla3[[#This Row],[CANT]]*5000000) -> 700000000 | F72: 8 | G72: =(Tabla3[[#This Row],[CANT2]]*10000000) -> 80000000 | H72: 75 | I72: =(Tabla3[[#This Row],[CANT3]]*7500000) -> 562500000 | J72: 48 | K72: =(Tabla3[[#This Row],[CANT4]]*500000) -> 24000000 | N72: 2 | O72: =(N72*200000) -> 400000 | P72: 20MHK | Q72: =(20*15000000) -> 300000000 | R72: =(Tabla3[[#This Row],[MONTO]]+Tabla3[[#This Row],[MONTO2]]+Tabla3[[#This Row],[MONTO3]]+Tabla3[[#This Row],[MONTO4]]+Tabla3[[#This Row],[MONTO5]]+Tabla3[[#This Row],[MONTO6]]+Tabla3[[#This Row],[MONTO7]]) -> 1666900000 | S72: =R72-(R72*10%) -> 1500210000 | T72: =(S72*1%) -> 15002100 | U72: =(Tabla3[[#This Row],[TOTAL -10%]]*Tabla3[[#This Row],[FIDUCIA]]) -> 0 | V72: =(Tabla3[[#This Row],[TOTAL -10%]]*Tabla3[[#This Row],[NUBE]]) -> 1485207900 | W72: SI | X72: NUBE | Y72: 0.01 | AA72: 0.99 | AB72: =SUM(Y72:AA72) -> 1 | AC72: =IF(AB72="","",IF(AB72=100%,"OK","ERROR")) -> OK
A73: =(A72+1) -> 53 | B73: 1094879054 | C73: JOHANNA BEDOYA SALGADO | D73: 20 | E73: =(Tabla3[[#This Row],[CANT]]*5000000) -> 100000000 | R73: =(Tabla3[[#This Row],[MONTO]]+Tabla3[[#This Row],[MONTO2]]+Tabla3[[#This Row],[MONTO3]]+Tabla3[[#This Row],[MONTO4]]+Tabla3[[#This Row],[MONTO5]]+Tabla3[[#This Row],[MONTO6]]+Tabla3[[#This Row],[MONTO7]]) -> 100000000 | S73: =R73-(R73*10%) -> 90000000 | T73: =(S73*1%) -> 900000 | U73: =(Tabla3[[#This Row],[TOTAL -10%]]*Tabla3[[#This Row],[FIDUCIA]]) -> 89100000 | V73: =(Tabla3[[#This Row],[TOTAL -10%]]*Tabla3[[#This Row],[NUBE]]) -> 0 | W73: SI | X73: FIDUCIA | Y73: 0.01 | Z73: 0.99 | AB73: =SUM(Y73:AA73) -> 1 | AC73: =IF(AB73="","",IF(AB73=100%,"OK","ERROR")) -> OK
A74: =(A73+1) -> 54 | B74: 98593548 | C74: JOHN BAYRON CARVAJAL MUÑOZ | D74: 2 | E74: =(Tabla3[[#This Row],[CANT]]*5000000) -> 10000000 | F74: 2 | G74: =(Tabla3[[#This Row],[CANT2]]*10000000) -> 20000000 | H74: 1 | I74: =(Tabla3[[#This Row],[CANT3]]*7500000) -> 7500000 | R74: =(Tabla3[[#This Row],[MONTO]]+Tabla3[[#This Row],[MONTO2]]+Tabla3[[#This Row],[MONTO3]]+Tabla3[[#This Row],[MONTO4]]+Tabla3[[#This Row],[MONTO5]]+Tabla3[[#This Row],[MONTO6]]+Tabla3[[#This Row],[MONTO7]]) -> 37500000 | S74: =R74-(R74*10%) -> 33750000 | T74: =(S74*1%) -> 337500 | U74: =(Tabla3[[#This Row],[TOTAL -10%]]*Tabla3[[#This Row],[FIDUCIA]]) -> 33412500 | V74: =(Tabla3[[#This Row],[TOTAL -10%]]*Tabla3[[#This Row],[NUBE]]) -> 0 | W74: SI | X74: FIDUCIA | Y74: 0.01 | Z74: 0.99 | AB74: =SUM(Y74:AA74) -> 1 | AC74: =IF(AB74="","",IF(AB74=100%,"OK","ERROR")) -> OK
A75: =(A74+1) -> 55 | B75: 1061822050 | C75: JOHN MICHAEL LOPEZ CORDOBA | D75: 1 | E75: =(Tabla3[[#This Row],[CANT]]*5000000) -> 5000000 | R75: =(Tabla3[[#This Row],[MONTO]]+Tabla3[[#This Row],[MONTO2]]+Tabla3[[#This Row],[MONTO3]]+Tabla3[[#This Row],[MONTO4]]+Tabla3[[#This Row],[MONTO5]]+Tabla3[[#This Row],[MONTO6]]+Tabla3[[#This Row],[MONTO7]]) -> 5000000 | S75: =R75-(R75*10%) -> 4500000 | T75: =(S75*1%) -> 45000 | U75: =(Tabla3[[#This Row],[TOTAL -10%]]*Tabla3[[#This Row],[FIDUCIA]]) -> 4455000 | V75: =(Tabla3[[#This Row],[TOTAL -10%]]*Tabla3[[#This Row],[NUBE]]) -> 0 | W75: SI | X75: FIDUCIA | Y75: 0.01 | Z75: 0.99 | AB75: =SUM(Y75:AA75) -> 1 | AC75: =IF(AB75="","",IF(AB75=100%,"OK","ERROR")) -> OK
A76: =(A75+1) -> 56 | B76: 7542612 | C76: JORGE ELIECER RODRIGUEZ CASTRO | D76: 45 | E76: =(Tabla3[[#This Row],[CANT]]*5000000) -> 225000000 | F76: 5 | G76: =(Tabla3[[#This Row],[CANT2]]*10000000) -> 50000000 | H76: 3 | I76: =(Tabla3[[#This Row],[CANT3]]*7500000) -> 22500000 | R76: =(Tabla3[[#This Row],[MONTO]]+Tabla3[[#This Row],[MONTO2]]+Tabla3[[#This Row],[MONTO3]]+Tabla3[[#This Row],[MONTO4]]+Tabla3[[#This Row],[MONTO5]]+Tabla3[[#This Row],[MONTO6]]+Tabla3[[#This Row],[MONTO7]]) -> 297500000 | S76: =R76-(R76*10%) -> 267750000 | T76: =(S76*1%) -> 2677500 | U76: =(Tabla3[[#This Row],[TOTAL -10%]]*Tabla3[[#This Row],[FIDUCIA]]) -> 265072500 | V76: =(Tabla3[[#This Row],[TOTAL -10%]]*Tabla3[[#This Row],[NUBE]]) -> 0 | W76: SI | X76: FIDUCIA | Y76: 0.01 | Z76: 0.99 | AB76: =SUM(Y76:AA76) -> 1 | AC76: =IF(AB76="","",IF(AB76=100%,"OK","ERROR")) -> OK
A77: =(A76+1) -> 57 | B77: 802700575 | C77: JORGE LUIS SOSA MERCADO | D77: 7 | E77: =(Tabla3[[#This Row],[CANT]]*5000000) -> 35000000 | F77: 19 | G77: =(Tabla3[[#This Row],[CANT2]]*10000000) -> 190000000 | H77: 9 | I77: =(Tabla3[[#This Row],[CANT3]]*7500000) -> 67500000 | R77: =(Tabla3[[#This Row],[MONTO]]+Tabla3[[#This Row],[MONTO2]]+Tabla3[[#This Row],[MONTO3]]+Tabla3[[#This Row],[MONTO4]]+Tabla3[[#This Row],[MONTO5]]+Tabla3[[#This Row],[MONTO6]]+Tabla3[[#This Row],[MONTO7]]) -> 292500000 | S77: =R77-(R77*10%) -> 263250000 | T77: =(S77*1%) -> 2632500 | U77: =(Tabla3[[#This Row],[TOTAL -10%]]*Tabla3[[#This Row],[FIDUCIA]]) -> 0 | V77: =(Tabla3[[#This Row],[TOTAL -10%]]*Tabla3[[#This Row],[NUBE]]) -> 260617500 | W77: SI | X77: NUBE | Y77: 0.01 | AA77: 0.99 | AB77: =SUM(Y77:AA77) -> 1 | AC77: =IF(AB77="","",IF(AB77=100%,"OK","ERROR")) -> OK
A78: =(A77+1) -> 58 | B78: E852841 | C78: JOSE ADOLFO RAMIREZ GALVIS | D78: 2 | E78: =(Tabla3[[#This Row],[CANT]]*5000000) -> 10000000 | F78: 3 | G78: =(Tabla3[[#This Row],[CANT2]]*10000000) -> 30000000 | R78: =(Tabla3[[#This Row],[MONTO]]+Tabla3[[#This Row],[MONTO2]]+Tabla3[[#This Row],[MONTO3]]+Tabla3[[#This Row],[MONTO4]]+Tabla3[[#This Row],[MONTO5]]+Tabla3[[#This Row],[MONTO6]]+Tabla3[[#This Row],[MONTO7]]) -> 40000000 | S78: =R78-(R78*10%) -> 36000000 | T78: =(S78*1%) -> 360000 | U78: =(Tabla3[[#This Row],[TOTAL -10%]]*Tabla3[[#This Row],[FIDUCIA]]) -> 0 | V78: =(Tabla3[[#This Row],[TOTAL -10%]]*Tabla3[[#This Row],[NUBE]]) -> 35640000 | W78: SI | X78: NUBE | Y78: 0.01 | AA78: 0.99 | AB78: =SUM(Y78:AA78) -> 1 | AC78: =IF(AB78="","",IF(AB78=100%,"OK","ERROR")) -> OK
A79: =(A78+1) -> 59 | B79: 17410384 | C79: JOSE ESTEBAN GOMEZ | D79: 10 | E79: =(Tabla3[[#This Row],[CANT]]*5000000) -> 50000000 | R79: =(Tabla3[[#This Row],[MONTO]]+Tabla3[[#This Row],[MONTO2]]+Tabla3[[#This Row],[MONTO3]]+Tabla3[[#This Row],[MONTO4]]+Tabla3[[#This Row],[MONTO5]]+Tabla3[[#This Row],[MONTO6]]+Tabla3[[#This Row],[MONTO7]]) -> 50000000 | S79: =R79-(R79*10%) -> 45000000 | T79: =(S79*1%) -> 450000 | U79: =(Tabla3[[#This Row],[TOTAL -10%]]*Tabla3[[#This Row],[FIDUCIA]]) -> 0 | V79: =(Tabla3[[#This Row],[TOTAL -10%]]*Tabla3[[#This Row],[NUBE]]) -> 44550000 | W79: SI | X79: NUBE | Y79: 0.01 | AA79: 0.99 | AB79: =SUM(Y79:AA79) -> 1 | AC79: =IF(AB79="","",IF(AB79=100%,"OK","ERROR")) -> OK
A80: =(A79+1) -> 60 | B80: 1097397130 | C80: JUAN PABLO SANCHEZ CARDONA | D80: 22 | E80: =(Tabla3[[#This Row],[CANT]]*5000000) -> 110000000 | F80: 5 | G80: =(Tabla3[[#This Row],[CANT2]]*10000000) -> 50000000 | R80: =(Tabla3[[#This Row],[MONTO]]+Tabla3[[#This Row],[MONTO2]]+Tabla3[[#This Row],[MONTO3]]+Tabla3[[#This Row],[MONTO4]]+Tabla3[[#This Row],[MONTO5]]+Tabla3[[#This Row],[MONTO6]]+Tabla3[[#This Row],[MONTO7]]) -> 160000000 | S80: =R80-(R80*10%) -> 144000000 | T80: =(S80*1%) -> 1440000 | U80: =(Tabla3[[#This Row],[TOTAL -10%]]*Tabla3[[#This Row],[FIDUCIA]]) -> 0 | V80: =(Tabla3[[#This Row],[TOTAL -10%]]*Tabla3[[#This Row],[NUBE]]) -> 142560000 | W80: SI | X80: NUBE | Y80: 0.01 | AA80: 0.99 | AB80: =SUM(Y80:AA80) -> 1 | AC80: =IF(AB80="","",IF(AB80=100%,"OK","ERROR")) -> OK
A81: =(A80+1) -> 61 | B81: 30856126 | C81: KATTYA MARGARITA LARIOS CARDONA | D81: 7 | E81: =(Tabla3[[#This Row],[CANT]]*5000000) -> 35000000 | F81: 7 | G81: =(Tabla3[[#This Row],[CANT2]]*10000000) -> 70000000 | R81: =(Tabla3[[#This Row],[MONTO]]+Tabla3[[#This Row],[MONTO2]]+Tabla3[[#This Row],[MONTO3]]+Tabla3[[#This Row],[MONTO4]]+Tabla3[[#This Row],[MONTO5]]+Tabla3[[#This Row],[MONTO6]]+Tabla3[[#This Row],[MONTO7]]) -> 105000000 | S81: =R81-(R81*10%) -> 94500000 | T81: =(S81*1%) -> 945000 | U81: =(Tabla3[[#This Row],[TOTAL -10%]]*Tabla3[[#This Row],[FIDUCIA]]) -> 0 | V81: =(Tabla3[[#This Row],[TOTAL -10%]]*Tabla3[[#This Row],[NUBE]]) -> 93555000 | W81: SI | X81: NUBE | Y81: 0.01 | AA81: 0.99 | AB81: =SUM(Y81:AA81) -> 1 | AC81: =IF(AB81="","",IF(AB81=100%,"OK","ERROR")) -> OK
A82: =(A81+1) -> 62 | B82: 1305590745 | C82: LAURA MERCEDES MÁRQUEZ YORENTE | D82: 5 | E82: =(Tabla3[[#This Row],[CANT]]*5000000) -> 25000000 | R82: =(Tabla3[[#This Row],[MONTO]]+Tabla3[[#This Row],[MONTO2]]+Tabla3[[#This Row],[MONTO3]]+Tabla3[[#This Row],[MONTO4]]+Tabla3[[#This Row],[MONTO5]]+Tabla3[[#This Row],[MONTO6]]+Tabla3[[#This Row],[MONTO7]]) -> 25000000 | S82: =R82-(R82*10%) -> 22500000 | T82: =(S82*1%) -> 225000 | U82: =(Tabla3[[#This Row],[TOTAL -10%]]*Tabla3[[#This Row],[FIDUCIA]]) -> 0 | V82: =(Tabla3[[#This Row],[TOTAL -10%]]*Tabla3[[#This Row],[NUBE]]) -> 22275000 | W82: SI | X82: NUBE | Y82: 0.01 | AA82: 0.99 | AB82: =SUM(Y82:AA82) -> 1 | AC82: =IF(AB82="","",IF(AB82=100%,"OK","ERROR")) -> OK
A83: =(A82+1) -> 63 | B83: 1088355401 | C83: LAURA REYES CASTAÑO | D83: 2 | E83: =(Tabla3[[#This Row],[CANT]]*5000000) -> 10000000 | R83: =(Tabla3[[#This Row],[MONTO]]+Tabla3[[#This Row],[MONTO2]]+Tabla3[[#This Row],[MONTO3]]+Tabla3[[#This Row],[MONTO4]]+Tabla3[[#This Row],[MONTO5]]+Tabla3[[#This Row],[MONTO6]]+Tabla3[[#This Row],[MONTO7]]) -> 10000000 | S83: =R83-(R83*10%) -> 9000000 | T83: =(S83*1%) -> 90000 | U83: =(Tabla3[[#This Row],[TOTAL -10%]]*Tabla3[[#This Row],[FIDUCIA]]) -> 0 | V83: =(Tabla3[[#This Row],[TOTAL -10%]]*Tabla3[[#This Row],[NUBE]]) -> 8910000 | W83: SI | X83: NUBE | Y83: 0.01 | AA83: 0.99 | AB83: =SUM(Y83:AA83) -> 1 | AC83: =IF(AB83="","",IF(AB83=100%,"OK","ERROR")) -> OK
A84: =(A83+1) -> 64 | B84: 10525194 | C84: LEON BOLIVAR LOPEZ SAMBONI | D84: 1 | E84: =(Tabla3[[#This Row],[CANT]]*5000000) -> 5000000 | R84: =(Tabla3[[#This Row],[MONTO]]+Tabla3[[#This Row],[MONTO2]]+Tabla3[[#This Row],[MONTO3]]+Tabla3[[#This Row],[MONTO4]]+Tabla3[[#This Row],[MONTO5]]+Tabla3[[#This Row],[MONTO6]]+Tabla3[[#This Row],[MONTO7]]) -> 5000000 | S84: =R84-(R84*10%) -> 4500000 | T84: =(S84*1%) -> 45000 | U84: =(Tabla3[[#This Row],[TOTAL -10%]]*Tabla3[[#This Row],[FIDUCIA]]) -> 4455000 | V84: =(Tabla3[[#This Row],[TOTAL -10%]]*Tabla3[[#This Row],[NUBE]]) -> 0 | W84: SI | X84: FIDUCIA | Y84: 0.01 | Z84: 0.99 | AB84: =SUM(Y84:AA84) -> 1 | AC84: =IF(AB84="","",IF(AB84=100%,"OK","ERROR")) -> OK
A85: =(A84+1) -> 65 | B85: 18502052 | C85: LISIMACO ARREDONDO RINCON | D85: 14 | E85: =(Tabla3[[#This Row],[CANT]]*5000000) -> 70000000 | H85: 1 | I85: =(Tabla3[[#This Row],[CANT3]]*7500000) -> 7500000 | R85: =(Tabla3[[#This Row],[MONTO]]+Tabla3[[#This Row],[MONTO2]]+Tabla3[[#This Row],[MONTO3]]+Tabla3[[#This Row],[MONTO4]]+Tabla3[[#This Row],[MONTO5]]+Tabla3[[#This Row],[MONTO6]]+Tabla3[[#This Row],[MONTO7]]) -> 77500000 | S85: =R85-(R85*10%) -> 69750000 | T85: =(S85*1%) -> 697500 | U85: =(Tabla3[[#This Row],[TOTAL -10%]]*Tabla3[[#This Row],[FIDUCIA]]) -> 69052500 | V85: =(Tabla3[[#This Row],[TOTAL -10%]]*Tabla3[[#This Row],[NUBE]]) -> 0 | W85: SI | X85: FIDUCIA | Y85: 0.01 | Z85: 0.99 | AB85: =SUM(Y85:AA85) -> 1 | AC85: =IF(AB85="","",IF(AB85=100%,"OK","ERROR")) -> OK
A86: =(A85+1) -> 66 | B86: 16216869 | C86: LUIS ALBERTO POSADA HERNANDEZ | D86: 1000 | E86: =(Tabla3[[#This Row],[CANT]]*5000000) -> 5000000000 | R86: =(Tabla3[[#This Row],[MONTO]]+Tabla3[[#This Row],[MONTO2]]+Tabla3[[#This Row],[MONTO3]]+Tabla3[[#This Row],[MONTO4]]+Tabla3[[#This Row],[MONTO5]]+Tabla3[[#This Row],[MONTO6]]+Tabla3[[#This Row],[MONTO7]]) -> 5000000000 | S86: =R86-(R86*10%) -> 4500000000 | T86: =(S86*1%) -> 45000000 | U86: =(Tabla3[[#This Row],[TOTAL -10%]]*Tabla3[[#This Row],[FIDUCIA]]) -> 0 | V86: =(Tabla3[[#This Row],[TOTAL -10%]]*Tabla3[[#This Row],[NUBE]]) -> 4455000000 | W86: SI | X86: NUBE | Y86: 0.01 | AA86: 0.99 | AB86: =SUM(Y86:AA86) -> 1 | AC86: =IF(AB86="","",IF(AB86=100%,"OK","ERROR")) -> OK
A87: =(A86+1) -> 67 | B87: 11301248 | C87: LUIS ALBERTO RODRIGUEZ SANCHEZ | D87: 48 | E87: =(Tabla3[[#This Row],[CANT]]*5000000) -> 240000000 | F87: 19 | G87: =(Tabla3[[#This Row],[CANT2]]*10000000) -> 190000000 | H87: 7 | I87: =(Tabla3[[#This Row],[CANT3]]*7500000) -> 52500000 | R87: =(Tabla3[[#This Row],[MONTO]]+Tabla3[[#This Row],[MONTO2]]+Tabla3[[#This Row],[MONTO3]]+Tabla3[[#This Row],[MONTO4]]+Tabla3[[#This Row],[MONTO5]]+Tabla3[[#This Row],[MONTO6]]+Tabla3[[#This Row],[MONTO7]]) -> 482500000 | S87: =R87-(R87*10%) -> 434250000 | T87: =(S87*1%) -> 4342500 | U87: =(Tabla3[[#This Row],[TOTAL -10%]]*Tabla3[[#This Row],[FIDUCIA]]) -> 429907500 | V87: =(Tabla3[[#This Row],[TOTAL -10%]]*Tabla3[[#This Row],[NUBE]]) -> 0 | W87: SI | X87: FIDUCIA | Y87: 0.01 | Z87: 0.99 | AB87: =SUM(Y87:AA87) -> 1 | AC87: =IF(AB87="","",IF(AB87=100%,"OK","ERROR")) -> OK
A88: =(A87+1) -> 68 | B88: 98430509 | C88: LUIS AVELINO PLAZA CASANOVA | D88: 5 | E88: =(Tabla3[[#This Row],[CANT]]*5000000) -> 25000000 | R88: =(Tabla3[[#This Row],[MONTO]]+Tabla3[[#This Row],[MONTO2]]+Tabla3[[#This Row],[MONTO3]]+Tabla3[[#This Row],[MONTO4]]+Tabla3[[#This Row],[MONTO5]]+Tabla3[[#This Row],[MONTO6]]+Tabla3[[#This Row],[MONTO7]]) -> 25000000 | S88: =R88-(R88*10%) -> 22500000 | T88: =(S88*1%) -> 225000 | U88: =(Tabla3[[#This Row],[TOTAL -10%]]*Tabla3[[#This Row],[FIDUCIA]]) -> 22275000 | V88: =(Tabla3[[#This Row],[TOTAL -10%]]*Tabla3[[#This Row],[NUBE]]) -> 0 | W88: SI | X88: FIDUCIA | Y88: 0.01 | Z88: 0.99 | AB88: =SUM(Y88:AA88) -> 1 | AC88: =IF(AB88="","",IF(AB88=100%,"OK","ERROR")) -> OK
A89: =(A88+1) -> 69 | B89: 11319563 | C89: LUIS CARLOS RODRIGUEZ CUBILLOS | D89: 2 | E89: =(Tabla3[[#This Row],[CANT]]*5000000) -> 10000000 | F89: 2 | G89: =(Tabla3[[#This Row],[CANT2]]*10000000) -> 20000000 | R89: =(Tabla3[[#This Row],[MONTO]]+Tabla3[[#This Row],[MONTO2]]+Tabla3[[#This Row],[MONTO3]]+Tabla3[[#This Row],[MONTO4]]+Tabla3[[#This Row],[MONTO5]]+Tabla3[[#This Row],[MONTO6]]+Tabla3[[#This Row],[MONTO7]]) -> 30000000 | S89: =R89-(R89*10%) -> 27000000 | T89: =(S89*1%) -> 270000 | U89: =(Tabla3[[#This Row],[TOTAL -10%]]*Tabla3[[#This Row],[FIDUCIA]]) -> 26730000 | V89: =(Tabla3[[#This Row],[TOTAL -10%]]*Tabla3[[#This Row],[NUBE]]) -> 0 | W89: SI | X89: FIDUCIA | Y89: 0.01 | Z89: 0.99 | AB89: =SUM(Y89:AA89) -> 1 | AC89: =IF(AB89="","",IF(AB89=100%,"OK","ERROR")) -> OK
A90: =(A89+1) -> 70 | B90: 12130726 | C90: LUIS EDUARDO HERNANDEZ CORTES | D90: 7 | E90: =(Tabla3[[#This Row],[CANT]]*5000000) -> 35000000 | R90: =(Tabla3[[#This Row],[MONTO]]+Tabla3[[#This Row],[MONTO2]]+Tabla3[[#This Row],[MONTO3]]+Tabla3[[#This Row],[MONTO4]]+Tabla3[[#This Row],[MONTO5]]+Tabla3[[#This Row],[MONTO6]]+Tabla3[[#This Row],[MONTO7]]) -> 35000000 | S90: =R90-(R90*10%) -> 31500000 | T90: =(S90*1%) -> 315000 | U90: =(Tabla3[[#This Row],[TOTAL -10%]]*Tabla3[[#This Row],[FIDUCIA]]) -> 0 | V90: =(Tabla3[[#This Row],[TOTAL -10%]]*Tabla3[[#This Row],[NUBE]]) -> 31185000 | W90: SI | X90: NUBE | Y90: 0.01 | AA90: 0.99 | AB90: =SUM(Y90:AA90) -> 1 | AC90: =IF(AB90="","",IF(AB90=100%,"OK","ERROR")) -> OK
A91: =(A90+1) -> 71 | B91: 16225101 | C91: LUIS FERNANDO CONTRERAS ARCILA | D91: 8 | E91: =(Tabla3[[#This Row],[CANT]]*5000000) -> 40000000 | F91: 2 | G91: =(Tabla3[[#This Row],[CANT2]]*10000000) -> 20000000 | R91: =(Tabla3[[#This Row],[MONTO]]+Tabla3[[#This Row],[MONTO2]]+Tabla3[[#This Row],[MONTO3]]+Tabla3[[#This Row],[MONTO4]]+Tabla3[[#This Row],[MONTO5]]+Tabla3[[#This Row],[MONTO6]]+Tabla3[[#This Row],[MONTO7]]) -> 60000000 | S91: =R91-(R91*10%) -> 54000000 | T91: =(S91*1%) -> 540000 | U91: =(Tabla3[[#This Row],[TOTAL -10%]]*Tabla3[[#This Row],[FIDUCIA]]) -> 0 | V91: =(Tabla3[[#This Row],[TOTAL -10%]]*Tabla3[[#This Row],[NUBE]]) -> 53460000 | W91: SI | X91: NUBE | Y91: 0.01 | AA91: 0.99 | AB91: =SUM(Y91:AA91) -> 1 | AC91: =IF(AB91="","",IF(AB91=100%,"OK","ERROR")) -> OK
A92: =(A91+1) -> 72 | B92: 801463712 | C92: LUIS VILLALBA QUIÑONEZ | D92: 2 | E92: =(Tabla3[[#This Row],[CANT]]*5000000) -> 10000000 | F92: 2 | G92: =(Tabla3[[#This Row],[CANT2]]*10000000) -> 20000000 | R92: =(Tabla3[[#This Row],[MONTO]]+Tabla3[[#This Row],[MONTO2]]+Tabla3[[#This Row],[MONTO3]]+Tabla3[[#This Row],[MONTO4]]+Tabla3[[#This Row],[MONTO5]]+Tabla3[[#This Row],[MONTO6]]+Tabla3[[#This Row],[MONTO7]]) -> 30000000 | S92: =R92-(R92*10%) -> 27000000 | T92: =(S92*1%) -> 270000 | U92: =(Tabla3[[#This Row],[TOTAL -10%]]*Tabla3[[#This Row],[FIDUCIA]]) -> 0 | V92: =(Tabla3[[#This Row],[TOTAL -10%]]*Tabla3[[#This Row],[NUBE]]) -> 26730000 | W92: SI | X92: NUBE | Y92: 0.01 | AA92: 0.99 | AB92: =SUM(Y92:AA92) -> 1 | AC92: =IF(AB92="","",IF(AB92=100%,"OK","ERROR")) -> OK
A93: =(A92+1) -> 73 | B93: 0802690271 | C93: LUZ ALBA CASTILLO CASTILLO | D93: 5 | E93: =(Tabla3[[#This Row],[CANT]]*5000000) -> 25000000 | R93: =(Tabla3[[#This Row],[MONTO]]+Tabla3[[#This Row],[MONTO2]]+Tabla3[[#This Row],[MONTO3]]+Tabla3[[#This Row],[MONTO4]]+Tabla3[[#This Row],[MONTO5]]+Tabla3[[#This Row],[MONTO6]]+Tabla3[[#This Row],[MONTO7]]) -> 25000000 | S93: =R93-(R93*10%) -> 22500000 | T93: =(S93*1%) -> 225000 | U93: =(Tabla3[[#This Row],[TOTAL -10%]]*Tabla3[[#This Row],[FIDUCIA]]) -> 0 | V93: =(Tabla3[[#This Row],[TOTAL -10%]]*Tabla3[[#This Row],[NUBE]]) -> 22275000 | W93: SI | X93: NUBE | Y93: 0.01 | AA93: 0.99 | AB93: =SUM(Y93:AA93) -> 1 | AC93: =IF(AB93="","",IF(AB93=100%,"OK","ERROR")) -> OK
A94: =(A93+1) -> 74 | B94: 26649101 | C94: LUZ ALBY FLÓREZ SERRATO | D94: 10 | E94: =(Tabla3[[#This Row],[CANT]]*5000000) -> 50000000 | R94: =(Tabla3[[#This Row],[MONTO]]+Tabla3[[#This Row],[MONTO2]]+Tabla3[[#This Row],[MONTO3]]+Tabla3[[#This Row],[MONTO4]]+Tabla3[[#This Row],[MONTO5]]+Tabla3[[#This Row],[MONTO6]]+Tabla3[[#This Row],[MONTO7]]) -> 50000000 | S94: =R94-(R94*10%) -> 45000000 | T94: =(S94*1%) -> 450000 | U94: =(Tabla3[[#This Row],[TOTAL -10%]]*Tabla3[[#This Row],[FIDUCIA]]) -> 0 | V94: =(Tabla3[[#This Row],[TOTAL -10%]]*Tabla3[[#This Row],[NUBE]]) -> 44550000 | W94: SI | X94: NUBE | Y94: 0.01 | AA94: 0.99 | AB94: =SUM(Y94:AA94) -> 1 | AC94: =IF(AB94="","",IF(AB94=100%,"OK","ERROR")) -> OK
A95: =(A94+1) -> 75 | B95: 42095093 | C95: LUZ MARIA CASTAÑO CORREA | D95: 15 | E95: =(Tabla3[[#This Row],[CANT]]*5000000) -> 75000000 | F95: 11 | G95: =(Tabla3[[#This Row],[CANT2]]*10000000) -> 110000000 | H95: 7 | I95: =(Tabla3[[#This Row],[CANT3]]*7500000) -> 52500000 | R95: =(Tabla3[[#This Row],[MONTO]]+Tabla3[[#This Row],[MONTO2]]+Tabla3[[#This Row],[MONTO3]]+Tabla3[[#This Row],[MONTO4]]+Tabla3[[#This Row],[MONTO5]]+Tabla3[[#This Row],[MONTO6]]+Tabla3[[#This Row],[MONTO7]]) -> 237500000 | S95: =R95-(R95*10%) -> 213750000 | T95: =(S95*1%) -> 2137500 | U95: =(Tabla3[[#This Row],[TOTAL -10%]]*Tabla3[[#This Row],[FIDUCIA]]) -> 0 | V95: =(Tabla3[[#This Row],[TOTAL -10%]]*Tabla3[[#This Row],[NUBE]]) -> 211612500 | W95: SI | X95: NUBE | Y95: 0.01 | AA95: 0.99 | AB95: =SUM(Y95:AA95) -> 1 | AC95: =IF(AB95="","",IF(AB95=100%,"OK","ERROR")) -> OK
A96: =(A95+1) -> 76 | B96: 10273172 | C96: MANFREDY ARMANDO SOLANO ZULUAGA | D96: 4 | E96: =(Tabla3[[#This Row],[CANT]]*5000000) -> 20000000 | F96: 3 | G96: =(Tabla3[[#This Row],[CANT2]]*10000000) -> 30000000 | H96: 2 | I96: =(Tabla3[[#This Row],[CANT3]]*7500000) -> 15000000 | R96: =(Tabla3[[#This Row],[MONTO]]+Tabla3[[#This Row],[MONTO2]]+Tabla3[[#This Row],[MONTO3]]+Tabla3[[#This Row],[MONTO4]]+Tabla3[[#This Row],[MONTO5]]+Tabla3[[#This Row],[MONTO6]]+Tabla3[[#This Row],[MONTO7]]) -> 65000000 | S96: =R96-(R96*10%) -> 58500000 | T96: =(S96*1%) -> 585000 | U96: =(Tabla3[[#This Row],[TOTAL -10%]]*Tabla3[[#This Row],[FIDUCIA]]) -> 57915000 | V96: =(Tabla3[[#This Row],[TOTAL -10%]]*Tabla3[[#This Row],[NUBE]]) -> 0 | W96: SI | X96: FIDUCIA | Y96: 0.01 | Z96: 0.99 | AB96: =SUM(Y96:AA96) -> 1 | AC96: =IF(AB96="","",IF(AB96=100%,"OK","ERROR")) -> OK
A97: =(A96+1) -> 77 | B97: 1121944121 | C97: MARIA CAMILA URAZAN BRICEÑO | D97: 7 | E97: =(Tabla3[[#This Row],[CANT]]*5000000) -> 35000000 | R97: =(Tabla3[[#This Row],[MONTO]]+Tabla3[[#This Row],[MONTO2]]+Tabla3[[#This Row],[MONTO3]]+Tabla3[[#This Row],[MONTO4]]+Tabla3[[#This Row],[MONTO5]]+Tabla3[[#This Row],[MONTO6]]+Tabla3[[#This Row],[MONTO7]]) -> 35000000 | S97: =R97-(R97*10%) -> 31500000 | T97: =(S97*1%) -> 315000 | U97: =(Tabla3[[#This Row],[TOTAL -10%]]*Tabla3[[#This Row],[FIDUCIA]]) -> 0 | V97: =(Tabla3[[#This Row],[TOTAL -10%]]*Tabla3[[#This Row],[NUBE]]) -> 31185000 | W97: SI | X97: NUBE | Y97: 0.01 | AA97: 0.99 | AB97: =SUM(Y97:AA97) -> 1 | AC97: =IF(AB97="","",IF(AB97=100%,"OK","ERROR")) -> OK
A98: =(A97+1) -> 78 | B98: 25170435 | C98: MARIA CLAUDIA BURITICA CORTEZ | D98: 7 | E98: =(Tabla3[[#This Row],[CANT]]*5000000) -> 35000000 | R98: =(Tabla3[[#This Row],[MONTO]]+Tabla3[[#This Row],[MONTO2]]+Tabla3[[#This Row],[MONTO3]]+Tabla3[[#This Row],[MONTO4]]+Tabla3[[#This Row],[MONTO5]]+Tabla3[[#This Row],[MONTO6]]+Tabla3[[#This Row],[MONTO7]]) -> 35000000 | S98: =R98-(R98*10%) -> 31500000 | T98: =(S98*1%) -> 315000 | U98: =(Tabla3[[#This Row],[TOTAL -10%]]*Tabla3[[#This Row],[FIDUCIA]]) -> 31185000 | V98: =(Tabla3[[#This Row],[TOTAL -10%]]*Tabla3[[#This Row],[NUBE]]) -> 0 | W98: SI | X98: FIDUCIA | Y98: 0.01 | Z98: 0.99 | AB98: =SUM(Y98:AA98) -> 1 | AC98: =IF(AB98="","",IF(AB98=100%,"OK","ERROR")) -> OK
A99: =(A98+1) -> 79 | B99: 34533946 | C99: MARIA DEL CARMEN ORTIZ LARA | D99: 2 | E99: =(Tabla3[[#This Row],[CANT]]*5000000) -> 10000000 | R99: =(Tabla3[[#This Row],[MONTO]]+Tabla3[[#This Row],[MONTO2]]+Tabla3[[#This Row],[MONTO3]]+Tabla3[[#This Row],[MONTO4]]+Tabla3[[#This Row],[MONTO5]]+Tabla3[[#This Row],[MONTO6]]+Tabla3[[#This Row],[MONTO7]]) -> 10000000 | S99: =R99-(R99*10%) -> 9000000 | T99: =(S99*1%) -> 90000 | U99: =(Tabla3[[#This Row],[TOTAL -10%]]*Tabla3[[#This Row],[FIDUCIA]]) -> 8910000 | V99: =(Tabla3[[#This Row],[TOTAL -10%]]*Tabla3[[#This Row],[NUBE]]) -> 0 | W99: SI | X99: FIDUCIA | Y99: 0.01 | Z99: 0.99 | AB99: =SUM(Y99:AA99) -> 1 | AC99: =IF(AB99="","",IF(AB99=100%,"OK","ERROR")) -> OK
A100: =(A99+1) -> 80 | B100: 29820961 | C100: MARIA ISABEL RAMIREZ CONTRERAS | D100: 5 | E100: =(Tabla3[[#This Row],[CANT]]*5000000) -> 25000000 | R100: =(Tabla3[[#This Row],[MONTO]]+Tabla3[[#This Row],[MONTO2]]+Tabla3[[#This Row],[MONTO3]]+Tabla3[[#This Row],[MONTO4]]+Tabla3[[#This Row],[MONTO5]]+Tabla3[[#This Row],[MONTO6]]+Tabla3[[#This Row],[MONTO7]]) -> 25000000 | S100: =R100-(R100*10%) -> 22500000 | T100: =(S100*1%) -> 225000 | U100: =(Tabla3[[#This Row],[TOTAL -10%]]*Tabla3[[#This Row],[FIDUCIA]]) -> 22275000 | V100: =(Tabla3[[#This Row],[TOTAL -10%]]*Tabla3[[#This Row],[NUBE]]) -> 0 | W100: SI | X100: FIDUCIA | Y100: 0.01 | Z100: 0.99 | AB100: =SUM(Y100:AA100) -> 1 | AC100: =IF(AB100="","",IF(AB100=100%,"OK","ERROR")) -> OK
A101: =(A100+1) -> 81 | B101: 24950300 | C101: MARIA LIGIA CASTAÑEDA MARIN | D101: 25 | E101: =(Tabla3[[#This Row],[CANT]]*5000000) -> 125000000 | F101: 14 | G101: =(Tabla3[[#This Row],[CANT2]]*10000000) -> 140000000 | H101: 4 | I101: =(Tabla3[[#This Row],[CANT3]]*7500000) -> 30000000 | J101: 1 | K101: =(Tabla3[[#This Row],[CANT4]]*500000) -> 500000 | R101: =(Tabla3[[#This Row],[MONTO]]+Tabla3[[#This Row],[MONTO2]]+Tabla3[[#This Row],[MONTO3]]+Tabla3[[#This Row],[MONTO4]]+Tabla3[[#This Row],[MONTO5]]+Tabla3[[#This Row],[MONTO6]]+Tabla3[[#This Row],[MONTO7]]) -> 295500000 | S101: =R101-(R101*10%) -> 265950000 | T101: =(S101*1%) -> 2659500 | U101: =(Tabla3[[#This Row],[TOTAL -10%]]*Tabla3[[#This Row],[FIDUCIA]]) -> 0 | V101: =(Tabla3[[#This Row],[TOTAL -10%]]*Tabla3[[#This Row],[NUBE]]) -> 263290500 | W101: SI | X101: NUBE | Y101: 0.01 | AA101: 0.99 | AB101: =SUM(Y101:AA101) -> 1 | AC101: =IF(AB101="","",IF(AB101=100%,"OK","ERROR")) -> OK
A102: =(A101+1) -> 82 | B102: 42064137 | C102: MARIA NANCY PALACIO GOMEZ | D102: 5 | E102: =(Tabla3[[#This Row],[CANT]]*5000000) -> 25000000 | R102: =(Tabla3[[#This Row],[MONTO]]+Tabla3[[#This Row],[MONTO2]]+Tabla3[[#This Row],[MONTO3]]+Tabla3[[#This Row],[MONTO4]]+Tabla3[[#This Row],[MONTO5]]+Tabla3[[#This Row],[MONTO6]]+Tabla3[[#This Row],[MONTO7]]) -> 25000000 | S102: =R102-(R102*10%) -> 22500000 | T102: =(S102*1%) -> 225000 | U102: =(Tabla3[[#This Row],[TOTAL -10%]]*Tabla3[[#This Row],[FIDUCIA]]) -> 22275000 | V102: =(Tabla3[[#This Row],[TOTAL -10%]]*Tabla3[[#This Row],[NUBE]]) -> 0 | W102: SI | X102: FIDUCIA | Y102: 0.01 | Z102: 0.99 | AB102: =SUM(Y102:AA102) -> 1 | AC102: =IF(AB102="","",IF(AB102=100%,"OK","ERROR")) -> OK
A103: =(A102+1) -> 83 | B103: 34537005 | C103: MARIA SONIA NARVAEZ | D103: 1 | E103: =(Tabla3[[#This Row],[CANT]]*5000000) -> 5000000 | R103: =(Tabla3[[#This Row],[MONTO]]+Tabla3[[#This Row],[MONTO2]]+Tabla3[[#This Row],[MONTO3]]+Tabla3[[#This Row],[MONTO4]]+Tabla3[[#This Row],[MONTO5]]+Tabla3[[#This Row],[MONTO6]]+Tabla3[[#This Row],[MONTO7]]) -> 5000000 | S103: =R103-(R103*10%) -> 4500000 | T103: =(S103*1%) -> 45000 | U103: =(Tabla3[[#This Row],[TOTAL -10%]]*Tabla3[[#This Row],[FIDUCIA]]) -> 4455000 | V103: =(Tabla3[[#This Row],[TOTAL -10%]]*Tabla3[[#This Row],[NUBE]]) -> 0 | W103: SI | X103: FIDUCIA | Y103: 0.01 | Z103: 0.99 | AB103: =SUM(Y103:AA103) -> 1 | AC103: =IF(AB103="","",IF(AB103=100%,"OK","ERROR")) -> OK
A104: =(A103+1) -> 84 | B104: 46640316 | C104: MARIA UMEIRA RAMIREZ ESCOBAR | D104: 6 | E104: =(Tabla3[[#This Row],[CANT]]*5000000) -> 30000000 | F104: 3 | G104: =(Tabla3[[#This Row],[CANT2]]*10000000) -> 30000000 | H104: 1 | I104: =(Tabla3[[#This Row],[CANT3]]*7500000) -> 7500000 | R104: =(Tabla3[[#This Row],[MONTO]]+Tabla3[[#This Row],[MONTO2]]+Tabla3[[#This Row],[MONTO3]]+Tabla3[[#This Row],[MONTO4]]+Tabla3[[#This Row],[MONTO5]]+Tabla3[[#This Row],[MONTO6]]+Tabla3[[#This Row],[MONTO7]]) -> 67500000 | S104: =R104-(R104*10%) -> 60750000 | T104: =(S104*1%) -> 607500 | U104: =(Tabla3[[#This Row],[TOTAL -10%]]*Tabla3[[#This Row],[FIDUCIA]]) -> 60142500 | V104: =(Tabla3[[#This Row],[TOTAL -10%]]*Tabla3[[#This Row],[NUBE]]) -> 0 | W104: SI | X104: FIDUCIA | Y104: 0.01 | Z104: 0.99 | AB104: =SUM(Y104:AA104) -> 1 | AC104: =IF(AB104="","",IF(AB104=100%,"OK","ERROR")) -> OK
A105: =(A104+1) -> 85 | B105: 49670323 | C105: MARILU ROPERO VIVAS | D105: 5 | E105: =(Tabla3[[#This Row],[CANT]]*5000000) -> 25000000 | F105: 2 | G105: =(Tabla3[[#This Row],[CANT2]]*10000000) -> 20000000 | H105: 2 | I105: =(Tabla3[[#This Row],[CANT3]]*7500000) -> 15000000 | R105: =(Tabla3[[#This Row],[MONTO]]+Tabla3[[#This Row],[MONTO2]]+Tabla3[[#This Row],[MONTO3]]+Tabla3[[#This Row],[MONTO4]]+Tabla3[[#This Row],[MONTO5]]+Tabla3[[#This Row],[MONTO6]]+Tabla3[[#This Row],[MONTO7]]) -> 60000000 | S105: =R105-(R105*10%) -> 54000000 | T105: =(S105*1%) -> 540000 | U105: =(Tabla3[[#This Row],[TOTAL -10%]]*Tabla3[[#This Row],[FIDUCIA]]) -> 0 | V105: =(Tabla3[[#This Row],[TOTAL -10%]]*Tabla3[[#This Row],[NUBE]]) -> 53460000 | W105: SI | X105: NUBE | Y105: 0.01 | AA105: 0.99 | AB105: =SUM(Y105:AA105) -> 1 | AC105: =IF(AB105="","",IF(AB105=100%,"OK","ERROR")) -> OK
A106: =(A105+1) -> 86 | B106: 38894024 | C106: MARINELA SALAZAR MARQUEZ | D106: 15 | E106: =(Tabla3[[#This Row],[CANT]]*5000000) -> 75000000 | F106: 12 | G106: =(Tabla3[[#This Row],[CANT2]]*10000000) -> 120000000 | H106: 4 | I106: =(Tabla3[[#This Row],[CANT3]]*7500000) -> 30000000 | J106: 1 | K106: =(Tabla3[[#This Row],[CANT4]]*500000) -> 500000 | R106: =(Tabla3[[#This Row],[MONTO]]+Tabla3[[#This Row],[MONTO2]]+Tabla3[[#This Row],[MONTO3]]+Tabla3[[#This Row],[MONTO4]]+Tabla3[[#This Row],[MONTO5]]+Tabla3[[#This Row],[MONTO6]]+Tabla3[[#This Row],[MONTO7]]) -> 225500000 | S106: =R106-(R106*10%) -> 202950000 | T106: =(S106*1%) -> 2029500 | U106: =(Tabla3[[#This Row],[TOTAL -10%]]*Tabla3[[#This Row],[FIDUCIA]]) -> 0 | V106: =(Tabla3[[#This Row],[TOTAL -10%]]*Tabla3[[#This Row],[NUBE]]) -> 200920500 | W106: SI | X106: NUBE | Y106: 0.01 | AA106: 0.99 | AB106: =SUM(Y106:AA106) -> 1 | AC106: =IF(AB106="","",IF(AB106=100%,"OK","ERROR")) -> OK
A107: =(A106+1) -> 87 | B107: 32535847 | C107: MARTA ELCY ALVAREZ PINEDA | D107: 5 | E107: =(Tabla3[[#This Row],[CANT]]*5000000) -> 25000000 | R107: =(Tabla3[[#This Row],[MONTO]]+Tabla3[[#This Row],[MONTO2]]+Tabla3[[#This Row],[MONTO3]]+Tabla3[[#This Row],[MONTO4]]+Tabla3[[#This Row],[MONTO5]]+Tabla3[[#This Row],[MONTO6]]+Tabla3[[#This Row],[MONTO7]]) -> 25000000 | S107: =R107-(R107*10%) -> 22500000 | T107: =(S107*1%) -> 225000 | U107: =(Tabla3[[#This Row],[TOTAL -10%]]*Tabla3[[#This Row],[FIDUCIA]]) -> 22275000 | V107: =(Tabla3[[#This Row],[TOTAL -10%]]*Tabla3[[#This Row],[NUBE]]) -> 0 | W107: SI | X107: FIDUCIA | Y107: 0.01 | Z107: 0.99 | AB107: =SUM(Y107:AA107) -> 1 | AC107: =IF(AB107="","",IF(AB107=100%,"OK","ERROR")) -> OK
A108: =(A107+1) -> 88 | B108: 38613836 | C108: MICAELA ANDREA BERGARA | D108: 5 | E108: =(Tabla3[[#This Row],[CANT]]*5000000) -> 25000000 | R108: =(Tabla3[[#This Row],[MONTO]]+Tabla3[[#This Row],[MONTO2]]+Tabla3[[#This Row],[MONTO3]]+Tabla3[[#This Row],[MONTO4]]+Tabla3[[#This Row],[MONTO5]]+Tabla3[[#This Row],[MONTO6]]+Tabla3[[#This Row],[MONTO7]]) -> 25000000 | S108: =R108-(R108*10%) -> 22500000 | T108: =(S108*1%) -> 225000 | U108: =(Tabla3[[#This Row],[TOTAL -10%]]*Tabla3[[#This Row],[FIDUCIA]]) -> 22275000 | V108: =(Tabla3[[#This Row],[TOTAL -10%]]*Tabla3[[#This Row],[NUBE]]) -> 0 | W108: SI | X108: FIDUCIA | Y108: 0.01 | Z108: 0.99 | AB108: =SUM(Y108:AA108) -> 1 | AC108: =IF(AB108="","",IF(AB108=100%,"OK","ERROR")) -> OK
A109: =(A108+1) -> 89 | B109: 1053864707 | C109: MICHAEL STEVEN GAVIRIA SANCHEZ | D109: 6 | E109: =(Tabla3[[#This Row],[CANT]]*5000000) -> 30000000 | R109: =(Tabla3[[#This Row],[MONTO]]+Tabla3[[#This Row],[MONTO2]]+Tabla3[[#This Row],[MONTO3]]+Tabla3[[#This Row],[MONTO4]]+Tabla3[[#This Row],[MONTO5]]+Tabla3[[#This Row],[MONTO6]]+Tabla3[[#This Row],[MONTO7]]) -> 30000000 | S109: =R109-(R109*10%) -> 27000000 | T109: =(S109*1%) -> 270000 | U109: =(Tabla3[[#This Row],[TOTAL -10%]]*Tabla3[[#This Row],[FIDUCIA]]) -> 26730000 | V109: =(Tabla3[[#This Row],[TOTAL -10%]]*Tabla3[[#This Row],[NUBE]]) -> 0 | W109: SI | X109: FIDUCIA | Y109: 0.01 | Z109: 0.99 | AB109: =SUM(Y109:AA109) -> 1 | AC109: =IF(AB109="","",IF(AB109=100%,"OK","ERROR")) -> OK
A110: =(A109+1) -> 90 | B110: 1010141206 | C110: MILLER LANDY PINEDA RAMIREZ | D110: 20 | E110: =(Tabla3[[#This Row],[CANT]]*5000000) -> 100000000 | R110: =(Tabla3[[#This Row],[MONTO]]+Tabla3[[#This Row],[MONTO2]]+Tabla3[[#This Row],[MONTO3]]+Tabla3[[#This Row],[MONTO4]]+Tabla3[[#This Row],[MONTO5]]+Tabla3[[#This Row],[MONTO6]]+Tabla3[[#This Row],[MONTO7]]) -> 100000000 | S110: =R110-(R110*10%) -> 90000000 | T110: =(S110*1%) -> 900000 | U110: =(Tabla3[[#This Row],[TOTAL -10%]]*Tabla3[[#This Row],[FIDUCIA]]) -> 89100000 | V110: =(Tabla3[[#This Row],[TOTAL -10%]]*Tabla3[[#This Row],[NUBE]]) -> 0 | X110: FIDUCIA | Y110: 0.01 | Z110: 0.99 | AB110: =SUM(Y110:AA110) -> 1 | AC110: =IF(AB110="","",IF(AB110=100%,"OK","ERROR")) -> OK
A111: =(A110+1) -> 91 | B111: 30346524 | C111: MIRIAM GOMEZ ESCOBAR | D111: 59 | E111: =(Tabla3[[#This Row],[CANT]]*5000000) -> 295000000 | F111: 8 | G111: =(Tabla3[[#This Row],[CANT2]]*10000000) -> 80000000 | H111: 8 | I111: =(Tabla3[[#This Row],[CANT3]]*7500000) -> 60000000 | J111: 1 | K111: =(Tabla3[[#This Row],[CANT4]]*500000) -> 500000 | N111: 1 | O111: =(Tabla3[[#This Row],[CANT6]]*200000) -> 200000 | P111: GOOGOPLEX | Q111: 500000000 | R111: =(Tabla3[[#This Row],[MONTO]]+Tabla3[[#This Row],[MONTO2]]+Tabla3[[#This Row],[MONTO3]]+Tabla3[[#This Row],[MONTO4]]+Tabla3[[#This Row],[MONTO5]]+Tabla3[[#This Row],[MONTO6]]+Tabla3[[#This Row],[MONTO7]]) -> 935700000 | S111: =R111-(R111*10%) -> 842130000 | T111: =(S111*1%) -> 8421300 | U111: =(Tabla3[[#This Row],[TOTAL -10%]]*Tabla3[[#This Row],[FIDUCIA]]) -> 0 | V111: =(Tabla3[[#This Row],[TOTAL -10%]]*Tabla3[[#This Row],[NUBE]]) -> 833708700 | X111: NUBE | Y111: 0.01 | AA111: 0.99 | AB111: =SUM(Y111:AA111) -> 1 | AC111: =IF(AB111="","",IF(AB111=100%,"OK","ERROR")) -> OK
A112: =(A111+1) -> 92 | B112: 91267483 | C112: NELSON VILLAMIZAR CELIS | D112: 11 | E112: =(Tabla3[[#This Row],[CANT]]*5000000) -> 55000000 | F112: 4 | G112: =(Tabla3[[#This Row],[CANT2]]*10000000) -> 40000000 | J112: 5 | K112: =(Tabla3[[#This Row],[CANT4]]*500000) -> 2500000 | R112: =(Tabla3[[#This Row],[MONTO]]+Tabla3[[#This Row],[MONTO2]]+Tabla3[[#This Row],[MONTO3]]+Tabla3[[#This Row],[MONTO4]]+Tabla3[[#This Row],[MONTO5]]+Tabla3[[#This Row],[MONTO6]]+Tabla3[[#This Row],[MONTO7]]) -> 97500000 | S112: =R112-(R112*10%) -> 87750000 | T112: =(S112*1%) -> 877500 | U112: =(Tabla3[[#This Row],[TOTAL -10%]]*Tabla3[[#This Row],[FIDUCIA]]) -> 0 | V112: =(Tabla3[[#This Row],[TOTAL -10%]]*Tabla3[[#This Row],[NUBE]]) -> 86872500 | X112: NUBE | Y112: 0.01 | AA112: 0.99 | AB112: =SUM(Y112:AA112) -> 1 | AC112: =IF(AB112="","",IF(AB112=100%,"OK","ERROR")) -> OK
A113: =(A112+1) -> 93 | B113: 1089906516 | C113: NOLVER MARTINEZ CASTRO | D113: 2 | E113: =(Tabla3[[#This Row],[CANT]]*5000000) -> 10000000 | R113: =(Tabla3[[#This Row],[MONTO]]+Tabla3[[#This Row],[MONTO2]]+Tabla3[[#This Row],[MONTO3]]+Tabla3[[#This Row],[MONTO4]]+Tabla3[[#This Row],[MONTO5]]+Tabla3[[#This Row],[MONTO6]]+Tabla3[[#This Row],[MONTO7]]) -> 10000000 | S113: =R113-(R113*10%) -> 9000000 | T113: =(S113*1%) -> 90000 | U113: =(Tabla3[[#This Row],[TOTAL -10%]]*Tabla3[[#This Row],[FIDUCIA]]) -> 8910000 | V113: =(Tabla3[[#This Row],[TOTAL -10%]]*Tabla3[[#This Row],[NUBE]]) -> 0 | X113: FIDUCIA | Y113: 0.01 | Z113: 0.99 | AB113: =SUM(Y113:AA113) -> 1 | AC113: =IF(AB113="","",IF(AB113=100%,"OK","ERROR")) -> OK
A114: =(A113+1) -> 94 | B114: 34567500 | C114: OLGA ALEXANDRA LOPEZ CAMACHO | D114: 14 | E114: =(Tabla3[[#This Row],[CANT]]*5000000) -> 70000000 | F114: 1 | G114: =(Tabla3[[#This Row],[CANT2]]*10000000) -> 10000000 | H114: 1 | I114: =(Tabla3[[#This Row],[CANT3]]*7500000) -> 7500000 | J114: 1 | K114: =(Tabla3[[#This Row],[CANT4]]*500000) -> 500000 | R114: =(Tabla3[[#This Row],[MONTO]]+Tabla3[[#This Row],[MONTO2]]+Tabla3[[#This Row],[MONTO3]]+Tabla3[[#This Row],[MONTO4]]+Tabla3[[#This Row],[MONTO5]]+Tabla3[[#This Row],[MONTO6]]+Tabla3[[#This Row],[MONTO7]]) -> 88000000 | S114: =R114-(R114*10%) -> 79200000 | T114: =(S114*1%) -> 792000 | U114: =(Tabla3[[#This Row],[TOTAL -10%]]*Tabla3[[#This Row],[FIDUCIA]]) -> 78408000 | V114: =(Tabla3[[#This Row],[TOTAL -10%]]*Tabla3[[#This Row],[NUBE]]) -> 0 | X114: FIDUCIA | Y114: 0.01 | Z114: 0.99 | AB114: =SUM(Y114:AA114) -> 1 | AC114: =IF(AB114="","",IF(AB114=100%,"OK","ERROR")) -> OK
...

Sheet RESUMEN INDIVIDUAL
O3: FECHA
O4: =TODAY() -> 46288
E5: LIDER: | F5: =('MATRIZ LISTADO'!D16) -> JOHANA CASTAÑEDA | O5: Consulta con el valor del dólar (TRM) Aquí | Q5: https://www.dolar-colombia.com/
O6: 3072.27
E7: NOMBRE | F7: =IFERROR(VLOOKUP(F8,'MATRIZ LISTADO'!B19:C144,2,0),"") -> JHON JADER OYOLA OSORIO | L7: =(F7) -> JHON JADER OYOLA OSORIO
E8: CC/ID/DNI | F8: 18510129 | L8: PAGO CON DESCUENTOS | P8: PESOS COLOMBIANOS
L9: PAGO TOTAL | O9: -0.1 | P9: =(G28*O6) -> 4017607479000
L10: 0.01 | O10: BANCO | P10: =(I14*O6) -> 40176074790
F11: CANT | G11: PAGO | I11: ORDEN DE PAGOS | L11: =IFERROR(VLOOKUP(F8,'MATRIZ LISTADO'!B19:AA144,25,0),"") -> 0 | O11: FIDUCIA | P11: =(I18*O6) -> 0
E12: QUINTILLION | F12: =IFERROR(VLOOKUP($F$8,Tabla3[[#All],[CC-ID-DNI]:[CANT]],3,0),"") -> 146 | G12: =IFERROR(VLOOKUP($F$8,Tabla3[[#All],[CC-ID-DNI]:[1% PAGO INICIAL]],4,0),"") -> 730000000 | I12: 1% PAGO BANCO | L12: =IFERROR(VLOOKUP(F8,'MATRIZ LISTADO'!B19:AB144,26,0),"") -> 0.99 | O12: NUBE | P12: =(I22*O6) -> 3977431404210
E14: NONGENTILLION | F14: =IFERROR(VLOOKUP($F$8,Tabla3[[CC-ID-DNI]:[1% PAGO INICIAL]],5,0),"") -> 60 | G14: =IFERROR(VLOOKUP($F$8,Tabla3[[#All],[CC-ID-DNI]:[1% PAGO INICIAL]],6,0),"") -> 600000000 | I14: =(G28*1%) -> 13077000
E16: VIGINTILLION | F16: =IFERROR(VLOOKUP($F$8,Tabla3[[CC-ID-DNI]:[1% PAGO INICIAL]],7,0),"") -> 16 | G16: =IFERROR(VLOOKUP($F$8,Tabla3[[#All],[CC-ID-DNI]:[1% PAGO INICIAL]],8,0),"") -> 120000000 | I16: FIDUCIA
E18: MONEDA DE ZIM | F18: =IFERROR(VLOOKUP($F$8,Tabla3[[CC-ID-DNI]:[1% PAGO INICIAL]],9,0),"") -> 6 | G18: =IFERROR(VLOOKUP($F$8,Tabla3[[#All],[CC-ID-DNI]:[1% PAGO INICIAL]],10,0),"") -> 3000000 | I18: =IFERROR(VLOOKUP(F8,Tabla3[[#All],[CC-ID-DNI]:[% NUBE]],20,0),"") -> 0
E20: BILLETE DE ZIMBABWE | F20: =IFERROR(VLOOKUP($F$8,Tabla3[[CC-ID-DNI]:[1% PAGO INICIAL]],11,0),"") -> 0 | G20: =IFERROR(VLOOKUP($F$8,Tabla3[[#All],[CC-ID-DNI]:[1% PAGO INICIAL]],12,0),"") -> 0 | I20: NUBE
E22: AGROCHEQUE ZIM | F22: =IFERROR(VLOOKUP($F$8,Tabla3[[CC-ID-DNI]:[1% PAGO INICIAL]],13,0),"") -> 0 | G22: =IFERROR(VLOOKUP($F$8,Tabla3[[#All],[CC-ID-DNI]:[1% PAGO INICIAL]],14,0),"") -> 0 | I22: =IFERROR(VLOOKUP(F8,Tabla3[[#All],[CC-ID-DNI]:[% NUBE]],21,0),"") -> 1294623000
E24: OTROS | F24: =IFERROR(VLOOKUP($F$8,Tabla3[[CC-ID-DNI]:[1% PAGO INICIAL]],15,0),"") -> 0 | G24: =IFERROR(VLOOKUP($F$8,Tabla3[[#All],[CC-ID-DNI]:[1% PAGO INICIAL]],16,0),"") -> 0
E26: TOTAL | G26: TOTAL -10%
E28: =SUM(G12:G24) -> 1453000000 | G28: =E28-(E28*10%) -> 1307700000

Sheet RESUMEN GENERAL
E3: LIDER: | F3: =('MATRIZ LISTADO'!D16) -> JOHANA CASTAÑEDA
F6: CANT | G6: PAGO
E7: QUINTILLION | F7: =SUM(Tabla3[CANT]) -> 2762 | G7: =(F7*5000000) -> 13810000000
E9: NONGENTILLION | F9: =SUM(Tabla3[CANT2]) -> 442 | G9: =(F9*10000000) -> 4420000000
E11: VIGINTILLION | F11: =SUM(Tabla3[CANT3]) -> 265 | G11: =(F11*7500000) -> 1987500000
E13: MONEDA DE ZIM | F13: =SUM(Tabla3[CANT4]) -> 75 | G13: =(F13*500000) -> 37500000
E15: BILLETE DE ZIMBABWE | F15: =SUM(Tabla3[CANT5]) -> 2 | G15: =(F15*12500000) -> 25000000
E17: AGROCHEQUE ZIM | F17: =SUM(Tabla3[CANT6]) -> 5 | G17: =(F17*500000) -> 2500000
E19: MHK | F19: 20 | G19: =(F19*15000000) -> 300000000
E21: GOOGOPLEX | F21: 1 | G21: =(F21*500000000) -> 500000000
E23: TOTAL | G23: TOTAL -10% | I23: 1% PAGO BANCO
E25: =SUM(G7:G21) -> 21082500000 | G25: =E25-(E25*10%) -> 18974250000 | I25: =(G25*1%) -> 189742500
